[
    {
        "제품카테고리": "구두",
        "제품명": "피카딜리 739026-1 펌프스_로즈 4.5CM 739026-1ROSE _s",
        "링크": "https://prod.danawa.com/info/?pcode=73623908&cate=18242491",
        "가격": "75,960",
        "상세설명": "구두 / 여성용 / 펌프스(미들힐)",
        "리뷰": [
            "리뷰 없음"
        ]
    },
    {
        "제품카테고리": "여성용",
        "제품명": "행텐 HT-222 여성 로퍼 드라이빙슈즈 스퀘어코 컴포트화 단화",
        "링크": "https://prod.danawa.com/info/?pcode=45146000&cate=18242491",
        "가격": "21,760",
        "상세설명": "여성용 / 로퍼",
        "리뷰": [
            "검정색 신발이 필요해서 급하게 구매하게 됐는데 배송도 빠르고 받아서 보니 기대 이상 입니다. 발도 편하고 가격대비 퀄리티도 좋네요. 다만 바닥 쿠션이 좀 부족해서 전에 사두었던 쿠션 깔창을 깔았더니 괜찮네요",
            "신발이 편하고 좋습니다.다른색상으로 하나더 구매하고싶네요",
            "제품은 괜찮아서 재구매했는데 포장이 이게 뭡니까!제품상자에다가 테이프를 덕지덕지 띁느라고 고생고생~~ 게다가 손가락 구멍까지...포장 신경 쓰세요",
            "요신발만신어요감사합니다",
            "배송도 신발도 맘에들어요대닥나세요",
            "신발이 편합니다. 감사합니다.",
            "행텐여성신발 저는 가볍구 폭신하고 바닥이 고무라서 더좋아여",
            "편하고 예쁘네요 좋아하는 스타일",
            "만족합니다 잘 받았습니다",
            "배송도빠르고 좋아요많이파세요",
            "문제없이 잘 도착하였습니다.",
            "잘받았습니다 ~^~~",
            "good",
            "볼이 넓어서 편안하그 조뫄요",
            "조아요조아요조아요참조아요",
            "조아요조아요조아요조아요 조아요 감사합니다",
            "좋아요",
            "너무 많이 좋아해요...",
            "편해요 가볍기도 하고 미끄럽지도 않아요",
            "신발 안쪽은 발이 엄청 편해요, 걸을때 바깥쪽 복사뼈에 약간 닿이는 느낌은 있는데 양말 신으면 괜찮을 것 같아요. 발 모양이 각자 다르고 복사뼈 높이도 각자 다르니까 참고만 하세요. 신발 튼튼해 보이고 편하니까 좋네요."
        ]
    },
    {
        "제품카테고리": "알 수 없음",
        "제품명": "셀린느 국내A/S가능 트리오페 미드 러버 레인부츠 장화 블랙 360117001C",
        "링크": "https://prod.danawa.com/info/?pcode=67640330&cate=18242491",
        "가격": "757,350",
        "상세설명": "여성용",
        "리뷰": [
            "리뷰 없음"
        ]
    },
    {
        "제품카테고리": "구두",
        "제품명": "락포트 토탈모션 카리라 펌프스 V78396",
        "링크": "https://prod.danawa.com/info/?pcode=4090549&cate=18242491",
        "가격": "95,210",
        "상세설명": "구두 / 여성용 / 펌프스(미들힐) / 굽종류: 스틸레토힐 / 민자 / 소재: 천연가죽 / 총굽: 5cm / 색상: 블랙 / 출시가: 250,000원",
        "리뷰": [
            "아이들 키우면서 구두를 자주 신지는 않는데 기본 스타일은 하나 구비되어 있어야 될 것 같아서 찾아보던 중에 지난번 락포트 슬링백도 편하게 잘 맞아서 락포트로 구매하게 되었어요좋아하는 디자인에 무난해서 옷 받쳐 입기에는 너무 편할 것 같고 다른 스틸레토 디자인 보다 발볼이 좀 넓은 편이라 시착만 해봤지만 많이 조이거나 불편하진 않습니다5cm 굽이라 안정감도 있고 안에 쿠션들이 잘 되어 있네요포장, 배송도 잘 되어서 왔습니다^^",
            "발볼있는 245라서 정사이즈 시켰는데 발뒤꿈치가 헐렁하게 남더라구요. 교환접수했더니 먼저 받은거 회수하는날 바로 교환품 받을수 있게 보내주셨어요. 이런 서비스 매우 만족합니다 예전에 여성브랜드 사ㅌ은 제가 구매하지도 않은 엉뚱한걸 보내서 교환요청하고 원래 구매했던 물품 보내달라니까 교환제품이 자기네 회사에 도착해서 검수까지 끝나야 발송해준다고 배짱영업하던데 말이죠~ 사이즈 교환하고 신어보니 아주 잘 맞고 편합니다",
            "신발은 빠르게 도착했어요 근데 신발에 기스가 너무 났어요 누가 신던거 보내신 느낌 들 정도로 디피 상품 보냈나 생각 들정도네오 반품 귀찮아서 급한대로 그냥 신어요 사이즈는 반 다운 했는데도 조금 여유롭네요 너무 싸게 구매해서 상태가 안좋은건지 ...",
            "락포트 신발 몇개있는데 너무 편하고 좋아서구두도 구매해요. 심플하고 너무 편해요.235사이즈인데 살짝 뒤가 남네요. 그래도 편하게 잘 신을듯 해요.",
            "정말 발 편하고 가죽도 매끈해서 만족. 사이즈는 좀 넉넉하니 참고하세요",
            "매장에서 신어보니 한사이즈 작게 사야 겠더라고요 처음 온 신발이 약간 찍혀있어서 한번 교환했는데 교환품은 괜찮았어요 매장보다 저렴하고 헤라랑 더스트백도 받고 좋습니다",
            "배송지연이었지만 받아서 다행이예요 선물했구요 포장은 안되어있지만 다행히 쇼핑백동봉해주셔서 잘 전했습니다 편하다고 해요 데일리로신기에 좋은신발입니다",
            "배송지연이었지만 받아서 다행이예요 선물했구요 포장은 안되어있지만 다행히 쇼핑백동봉해주셔서 잘 전했습니다 편하다고 해요 데일리로신기에 좋은신발입니다",
            "격식있는 자리에 갈때 무난하게 신으려고 구입했어요.신발은 편하고 깔끔합니다.",
            "좋은 가격에 잘 구매했습니다. 무조건 반사이즈 작게 주문해야합니다. 폭신폭신하고 발이 편한 구두입니다.",
            "앞코쪽에 스크래치가 있어서 반품할까하다가 그냥 신기로 했어요. 심플하고 편하고 소가죽이 견고하다고 해야할까요? 어쨌든 마음에 듭니다.",
            "발볼 넓은 편이라 앞쪽이 좁아서 아파요 ㅠ 락포트매니아인데 제가 산 락포트 중에 제일 편하지 않아요",
            "백화점 상품이라 배송 기대를 안 했는데 기대보다 빨리 도착했어요. 포장도 깔끔하게 신경써서 보내주셨네요. 사이즈는 아주 약간 크기 나온 느낌이지만 락포트인만큼 아주 편하게 신을 수 있을 듯 합니다.",
            "몇번 신은후 길을 들이니 편합니다. 제 발볼이 넓어 한치수 크게 시켰는데도 처음 몆번은 힘드네요~ 그 이후는 편하게 잘 신어요",
            "깨끗하고 좋은 신발이 왔네요. 딸이 엄청 편한데 약간 크다네요 깔창을 하나 깔아야할까봐요...",
            "배송빠르네요. 지인이 편하다고 구매해봤는데 너무 좋네요. 사이즈는 평소보다 한치수 작게하니 딱 맞아요.",
            "딸 실기시험때 신는 구두 선택했어요 바로 기숙사로 보내서 느낌은 잘 모르겠지만 보이기엔 편해 보여요잘 신어 보겠습니다 사진 보내 줬어요",
            "좋은 가격에 잘 구매했습니다.저렴하게 잘 사고 와이프가 발도 편하다고 하네요",
            "구두 240신는데 235주문했더니 잘 맞습니다. 배송 빠르고 포장도 깔끔하게 해서 보내주셔서 맘에 들어요",
            "구두 240신는데 235주문했더니 잘 맞습니다. 배송 빠르고 포장도 깔끔하게 해서 보내주셔서 맘에 들어요"
        ]
    },
    {
        "제품카테고리": "여성용",
        "제품명": "크록스 여성 브루클린 플랫 슈즈_209384-6UR",
        "링크": "https://prod.danawa.com/info/?pcode=56173700&cate=18242491",
        "가격": "30,532",
        "상세설명": "여성용 / 플랫 / 소재: PU",
        "리뷰": [
            "핑크빛의 플랫슈즈 입니다.평소 구두 250 사이즈를 딱 맞게 신는데이 신발은 길이나, 발 볼이 여유있습니다.이 신발로 245정도면 딱 맞을 것 같습니다.우리가 많이 신는 크록스와 비슷한 느낌이라서오랜시간 걸으면 발뒤꿈치가 아플 것 같지만,말랑말랑한 고무라서 가까운 거리는 편하게 신고다닐 수 있을 것 같습니다.신었을 때 발이 날렵하게 예뻐보이기보다는, 동글동글 귀엽게 보이는 디자인입니다.발가락 부분이 좁아지지 않아서 발이 편합니다.동네에서 편하게 신고다닐 수 있는 신발입니다.가격대비 만족합니다.",
            "오른쪽 신발이 크게 나왔어오",
            "편하고 아주만족합니다",
            "사이즈가 너무크게나와서 어터케할지모른겟어요",
            "가볍고 편해서 검정 구매후 재구매 했어요",
            "편하고 맘에 들어요~~^^"
        ]
    },
    {
        "제품카테고리": "알 수 없음",
        "제품명": "셀린느 356834582C 38NO",
        "링크": "https://prod.danawa.com/info/?pcode=65242487&cate=18242491",
        "가격": "1,185,720",
        "상세설명": "여성용",
        "리뷰": [
            "리뷰 없음"
        ]
    },
    {
        "제품카테고리": "여성용",
        "제품명": "누오보 카란 1 NC30647 BLACK",
        "링크": "https://prod.danawa.com/info/?pcode=65360426&cate=18242491",
        "가격": "23,911",
        "상세설명": "여성용 / 로퍼",
        "리뷰": [
            "리뷰 없음"
        ]
    },
    {
        "제품카테고리": "구두",
        "제품명": "흐꺙 하모니 발레리나 플랫 TT-00055",
        "링크": "https://prod.danawa.com/info/?pcode=16738259&cate=18242491",
        "가격": "147,900",
        "상세설명": "구두 / 여성용 / 플랫 / 장식 / 소재: 천연가죽 / 색상: 블랑 / 출시가: 148,000원",
        "리뷰": [
            "검정색 잘 신고 있어서 밝은색으로 추가 구매했어요. 흐꺙 얇기는 하지만 정말 편하고 구매할때마다 만족하는 브랜드예요. 평소에 235-240 사이즈 신어요. 보통 운동화는 240 신는편인데 흐꺙은 37 신어요. 해당 페이지 안내로 37인 230-235인데 괜찮아오!",
            "유명해서 한번 신어보고 싶엇는데 방송하길래 봄맞이 신발로 구매했어요.디자인 심플하고 바닥이 몰랑해서 신었을때 편한거 같아요.",
            "245사이즈인데 흐꺙은 항상 39사이즈 아주 편하게 잘 신고있어요. 사진과같아요 마음에들어요.",
            "8만원대로 저렴하게 잘 샀어요! 원래 신던건데 1년 신으면 새로 바꿔줘야해요. 스웨이드라 쉽게 더러워져요.",
            "블랙 있어서 화이트도 샀어요이뻐요 배송은 적당히 빠르게 왔습니다",
            "좋은 가격에 잘 구매했습니다.",
            "배송 엄청나게 빨라요 저렴하게 잘 샀어요",
            "귀엽고좋아요! 다른색도 사고싶어요",
            "예쁘네요 번창하세요 ㅎㅎ",
            "넘예뻐요 가볍고 편해요",
            "편하고 정말 예뻐요",
            "착화감 너무 좋구요 저렴하게 구매해서 좋아여",
            "너무 빨리 더러워져요",
            "여름에 신기 딱 좋아요가볍고 예쁘네요매우 만족입니다~~~~~~~~~~~~~~~~~~~~~~~~~~~~~~^^",
            "발진짜편해요250에 발볼이있어서 편하게신으려고 40사이즈 주문했어요 첫날 어?좀 불편한가?싶었는데 두번째신은날 덧신 신은거마냥 엄첫 편해서 쇼핑한다고 많이 걸었는데 정말편했어요 발바닥도 하나도 안아파요 주변에도 추전해서 구매했구요 깔별로 모으고 싶은 마음이 생기네요H몰에도 다양한 색상이 입고 되었으면 합니다",
            "평소에 235-240mm 신는데 이 제품은 37사이즈로 구매했습니다. 저는 이 제품 구매 전에 흐? 같은 제품인데 블랙 색상으로 착용해본 적이 있어서 37사이즈로 똑같이 재구매했고 화이트 색상 너무 예쁘네요! 봄여름에 잘 신을 수 있을 것 같아요??",
            "완전 하얀 흰색임. 발이 플랫치고 편함. 가죽이 부들부들해서 맨발에도 괜찮을듯. 자주 신어질듯함. 다양한 색상이 입고되면 더 좋을듯. 검정색도 교환이 빨리되면 좋겠음.",
            "스웨이드 구입했을때 38사이즈가 좀 여유있었어서 37했는데 딱 맞아요 가죽이라 늘림가능할듯 하서 그냥 구매확정요 흰색이라 코디기대되요^^",
            "정사이즈로 구매 했는데 사이즈 잘 맞아요~무겁다는 후기가 있어 걱정했는데…..가볍고 발도 편하네요~~~ 너무 맘에 들어요 추천합니다",
            "너무 마음에 들어요! 추천합니다. 두꺼운 양말에 레이어드 하려고 230샀는데 조금 딱 맞아요 한치수 크게 사세요!!"
        ]
    },
    {
        "제품카테고리": "구두",
        "제품명": "세라 BR 앤코 여성 러블리 기본 스틸레토 펌프스 7CM A22P409 스킨베이지",
        "링크": "https://prod.danawa.com/info/?pcode=91741721&cate=18242491",
        "가격": "152,570",
        "상세설명": "구두 / 여성용 / 펌프스(미들힐)",
        "리뷰": [
            "리뷰 없음"
        ]
    },
    {
        "제품카테고리": "알 수 없음",
        "제품명": "츄바스코 이누이트 이누이트x 세렌 메리제인 샌들 CSR-1830-00",
        "링크": "https://prod.danawa.com/info/?pcode=89768381&cate=18242491",
        "가격": "46,180",
        "상세설명": "메리제인",
        "리뷰": [
            "리뷰 없음"
        ]
    },
    {
        "제품카테고리": "구두",
        "제품명": "나인웨스트 이태리 양가죽 크리스탈 플랫 NW022",
        "링크": "https://prod.danawa.com/info/?pcode=13666493&cate=18242491",
        "가격": "98,510",
        "상세설명": "구두 / 여성용 / 플랫 / 장식 / 소재: 천연가죽 / 총굽: 3cm / 색상: 블랙, 베이지, 코랄, 민트, 실버, 옐로우",
        "리뷰": [
            "집안에서 시착 해보니 바닥도 푹신 푹신 하고 뒤꿈치도 까질거 같지 않고 편해 보여요.큐빅 장식이 예뻐요.발가락 양옆에 가죽 이은부분이 자국이 남는데 오래 신어도 아프지 않을지 신경이 쓰여요.디자인이 살짝 나이 들어 보이긴 합니다.",
            "블랙 옐로 2개 주문했는데 블랙만 먼저 왔어요. 발볼이 좁아 한사이즈 더 크게 주문했더니 정말 편하네요. 베이지색도 주문하고 싶은데 품절이라 아쉬워요.",
            "처음 신어 봐도 발이 불편한 면은 그닥 없었어요화사한 색상이라 선택했고 신발디자인은 애매한듯 해요",
            "세일가격에 완전 득템했어요 . 가죽 부드럽고 가볍고 바닥도 말랑하고 너무 편해요",
            "블랙 정사이즈가 불편해서한사이즈 업해서 주문약간크네요정사이즈는 앞볼이 쪼이고한사이즈 업하니 좀크고 그러네요어째든 예쁘고 편해서그냥 신을겁니다",
            "가격도 착한데 착화감도 너무 좋아요. 가죽도 부들부들하고 마음에 듭니다",
            "큐빅장식과 매듭이 양쪽 다름... 교환해도 별다를것 같지않아 그냥 착용합니다.. 편하고 디자인과 가죽상태는 좋아요...",
            "빠른배송 잘받앗슴다 감사함다 좋아여 ㅎ 이뿌네여 양가죽이라부드러워구매 새신을신으면뒷꿈치,발가락이 까져서고생하거든요 ㅎㅠ그래서부드러운양가죽이라고해서구매햇어요굽높이두쪼금잇고해서 ~~ㅎ",
            "발이 편해서 애착구두가 됐어요. 여름에 신기에 아주 시원한 색상입니다.",
            "너무 마음에 들어요! 추천합니다. 포장도 잘 되었고 역시 브랜드제품이 다르군요. 배송이 빠릅니다. 좋은제품을 좋은 가격에 구입하게 해 주셔서 감사드립니다.",
            "소재좋고쿠션감좋은데 발볼넓어서좀 쪼입니다하지만 착용하고 시간이 좀지나니편해졌어요계속신으면 늘어날듯요",
            "왼발이 좀작은데 오른발은 엄청 편해요.신발을 살때마다. 왼쪽 발이 항상 작아요ㅠ엄지있는데가 왼발만 튀어 나와서 살때 마다 고민이네요.",
            "발이 작아 220신는데...작은사이즈가 225부터 시작이라 주문했는데 예쁘고 잘 맞아요.블랙 재구매 하려구요~",
            "사이즈가 조금 적게 나와서 어머니 드렸어요.예쁘고 착화감이 좋아요",
            "발모양도 예쁘고 재질이 고급스러운 며 마음에 들어요",
            "디자인은 예쁜데 볼이 좀 쪼여 조금 불편 하네요.",
            "두개째예요.완전 편해요~저렴한 가격에 구입해서 정말 좋아요강추입니다.",
            "상품 받아보고 예뻤어요 발볼도 적당하고 편해요",
            "가죽도 보들보들하고,디자인도 예뻐요~",
            "한사이즈 업해서 신으니 편해요. 사진보다 실물이 훨씬 예쁩니다."
        ]
    },
    {
        "제품카테고리": "구두",
        "제품명": "레이첼콕스 Sally R1359",
        "링크": "https://prod.danawa.com/info/?pcode=3569907&cate=18242491",
        "가격": "135,800",
        "상세설명": "구두 / 여성용 / 펌프스(하이힐) / 굽종류: 스틸레토힐 , 가보시힐 / 민자 / 소재: 천연가죽 / 총굽: 9cm (굽 높이 변경 가능) / 색상: 블랙, 마브, 버건디, 스킨, 그레이, 라이트 그레이, 스킨 베이지, 블랙 에이, 화이트, 스카이블루, 핑크",
        "리뷰": [
            "사이즈 잘 맞구요 새구두라선지 발볼이 좀 불편해요만족합니다",
            "잘 신고 있어요사이즈도 잘 맞구요다만 제가 발볼이 넓다보니 조금 꽉끼는게 불편하긴 하지만 이쁘게 잘 신고있습니다",
            "역시 신발은 레이첼콕스에요.높은굽에도 발이 부담스럽지 않고 편해요.와이드청바지에나 슬랙스에 딱이에요",
            "편안하고 좋아요 사이즈 5정도 크게 사야맞네요",
            "발이너무아파요ㅜㅜ 못신을듯",
            "너무 높은 높이 때문일까요 엄지로 이어지는 발가락 뼈가 힘을 받으며 도드라지면서 구두에 닿게 되는데 구두마감이 생각보다 날카로워서 결국 반나절만에 발가락이 까지고 피가났습니다 못 신어요 신고 지내던 편하기로 유명한 타회사 제품은 닿은 면이 모두 부드러워서 발등이 닿아도 상처가 나지 않던데, 디자인보고 구매하니 이런 실패를 하네요 앞으로 구두는 함부로 온라인으로 못사겠어요 (물론 언급했던 타회사 제품은 온라인 구매를 했어도 성공이었어요) 가보시때문에 교환환불 안된다고 하니 버려야겠네요",
            "평소 235신어서 이 제품도 235로 구매 했습니다. 사이즈가 살짝 낙낙하네요. 한치수 작은걸 구매하기엔 약간 모험인거 같구요.같이 보내주신 깔창을 깔고 신으니 딱 맞는 느낌입니다. 아침에 신을때 낙낙하다가 오후에 발이 좀 부으면 맞는 느낌인것 같아요.마브 컬러 주문했는데 제 피부가 그렇게 하얀 편이 아니어서 그런지 스킨색보다자연스러워 보여서 맘에 드네요.",
            "색은 화면 그대로여서 만족합니다~ 그러나, 걸을때 굽이 뒤로 빠지고 그래서 밀리는 소리가 덜걱덜걱 나요... 굽 잘못 제작됐을때 굽 뒤로 빠지는 그 느낌 아시는분은 아실거예요... 제작기간은 오래걸리는거 감안했었고, 발볼은 많이 늘려 헐거울까봐 굽넓힘 신청안했더니(구두방에서 늘려신을 생각하고) 칼발이 아닌 제발에쪼이긴 하네요....",
            "스킨색 구두검색을 하다가 여기 함 사봤어요^^휴가기간에 배송늦고 어쩌고 거의 3주만에 받았...근데 신발은 괜찮아보이네요하도 험하게 신발을 신어서 뒤축떨어지고 앞코 난리나고 맨날 그러는데 이거 단단해보여요배송만 좀 빠르면 좋겠어요^^;;3주동안 스니커즈만 내리신고..ㅎㅎ내구성 보고 재주문하든지 하께요..",
            "라인이나 마감처리나 다 괜찮고 좋은데.. 솔직히 착화감이 생각보다 편하진 않네요ㅠㅠ 유광이라 그럴지도 모르긴 하는데 타사에서 같은 굽 높이에 비슷한 라인의 구두는 신고 달리고 많이 걷기도 했지만 진짜 편했거든요. 그거 생각하고 보름을 기다렸는데.. 착화감은 기대에 못미쳐요. 무튼 색은 생각했던 색이라 예뻤어요",
            "신발 라인은 정말 이쁩니다딸 신으려고 구입했는데 좀 크고 발 아치 부분이 좀 많이 떠서 신을때 편할지는 모르겠어요일단 신기로 했구요배송은 2주가 지날때 스킨색이라 연해서 검수할때 문제가 있다며전화로 더 늦은 배송을 하겠다고전화와서 오래 기다려서또 취소하고 다시 주문하기도곤란해 기다려 좀 늦게 받았네요",
            "옵션 변경하고 추가해서 어찌될까 좀 걱정했는데 너무 이쁘게 원하던대로 잘 도착했어요. 전화 상담도 친절하게 받아주시고 아주아주 만족해요~☆ 다만 속가보시 추가시에는 한사이즈 크게 주문하면 좋을듯해요. 이것저것 변경한터라 교환/반품도 안되서 어찌해야할지 신지도 못하고 몹시 난감한 상황이네요...ㅠㅜ",
            "그렇게 오래 기다려서 받을 정도의 제품 품질은 아니네요. 전체적으로 고품질은 아닌. 살짝 엉성한 느낌이기도.. 굽에 본드칠 같기도 하고 가죽이 벗겨진 것 같기도 한 자국이 있어요. 맞춤이라면서 뭐 이런 오염이 있나 싶어 반품할까 어쩔까 고민.. 귀찮아서 그냥 신기로..",
            "9cm 샀는데 약간 높긴 하지만 굽에 비해 착화감 아주 좋음. 정사이즈로 주문 했는데 신었을 때 좀 컸지만 같이 보내준 깔창 덕분에 기분이 아주 좋음. 다음엔 깔별로 굽 8cm로 사야겠음. 아 그리고 구매 전 주의 사항은 배송기간이 미친듯이엄청엄청엄처어어어어엉나게 김.",
            "9cm 샀는데 약간 높긴 하지만 굽에 비해 착화감 아주 좋음. 정사이즈로 주문 했는데 신었을 때 좀 컸지만 같이 보내준 깔창 덕분에 기분이 아주 좋음. 다음엔 깔별로 굽 8cm로 사야겠음. 아 그리고 구매 전 주의 사항은 배송기간이 미친듯이엄청엄청엄처어어어어엉나게 김.",
            "가죽이 단단한 편이어서 처음 신었을 때에는 발이 조금 아팠어요. 그래도 가죽인라 내 발에 맞게 늘어나서 여러번 신다보니 제 발에 맞게 바뀌네요 ㅎ 발목부분이 벗겨지지 않게 마찰력이 큰 소재로 처리가 되어있는 점이 좋았어요. 모양은 보시는대로!!",
            "제가 같은제품이4개가 있는데 이번에 온 제품은 사이즈가 너무 큽니다 다시 제작해주시던 교환이든 반품이든 해주셔야할것 같습니다 제가 그동안 구매한 내역 확인해보시면 됩니다 가보시도 모두 추가했던 제품들입니다",
            "기본스탈로 신기엔 이브랜드가 가격도 착하고 굽모양이나 착화감이 좋아 계속 구입하게되네요 뒷꿈치까임도 없고 첫날부터 편하게신었습니다 9센치가 신었을때 가장 이쁜것같아요",
            "배송은 2주 정도 걸렸구요 사이즈는 정사이즈 앞코가 짧아서 발가락 보여요 스타킹신으니 좀 괜찮음 디자인이 이뻐서 세련되보이고 날씬해보임",
            "상품 배송이 얼마 늦지도 않았는데도 사과 전화도 주시고, 감사 카드와 사은품까지 챙겨주셨네요. 제품도 훌륭하지만 고객을 생각해 주시는 마음이 무척 감동이네요. 잘 신을게요. 감사합니다.^^*"
        ]
    },
    {
        "제품카테고리": "구두",
        "제품명": "핏플랍 알레그로 레더 버클 로퍼 FFSO3E021W1",
        "링크": "https://prod.danawa.com/info/?pcode=18872774&cate=18242491",
        "가격": "53,590",
        "상세설명": "구두 / 여성용 / 체인로퍼(장식) / U팁 / 소재: 천연가죽 / 총굽: 3cm / 색상: 라이트브라운 / 출시가: 229,000원",
        "리뷰": [
            "무지외반증 발여서 신발 구입할때마다 실패여요. 그러나 핏플랍은 변함없이 착화감 좋고 너무너무 편하네요~ 굽이 조금 높았으면 더할나위 없어요~",
            "편안신발오랜만 아주좋아요 추천",
            "신어보고 주문한거라 가볍고 발이 편합니다. 저렴하게 구이입해서 좋고 예쁘기까지 하네요. 포장도 예쁘게 잘왔고 매장 직원의 예쁜 손편지 카드까지 이렇게 상품구입하고 기분 좋은 날은 처음이라 감사해요~^^",
            "정사이즈로 나온 것 같아요. 색상 예뻐요.",
            "크림이 없어 브라운으로 신기 편안합니다",
            "발볼도 넓어보이지 않고 발도 작아보이고 좋네요",
            "발은편하고좋은데 색상이 화면이랑 쫌 많이차이나네요.",
            "뒷밴딩이라 앞으로 밀리는 느낌. 여유있게 샀는데 볼이 넓다보니 조금 불편해요.ㅠㅠ",
            "거의 피플랍을 신는데 이제품은 정사이즈가 작아서 한사이즈위로 교환했는데 약간큰듯 편하게 잘맞네요 가죽이 좋아요 이 밑창인제품은 바닥이 편해요",
            "부라운사고이번엔크림삿어요넘좋아요",
            "사이즈가 좀 애매해서 매장가서 같은 디자인 신발 신어보고 주문합니다정사이즈 입니다양가죽이라 부드러워 그런지 살짝 큰듯 합니다신다보면 늘어날거 감안해서 저는 정사이즈 샀네요로퍼 몇번 사서 죄다 뒷꿈치가 상처나서 몇번 신어보지도 못하고 버린 아픔이있어서 많이 고민했는데 핏플랍은 워낙 편한신발로 유명하기도 하고 해서 한번신어보려고 합니다매장에서도 워낙 쿠션좋고 부드러워서 덧신신고 신는거 제일 추천한다 하시던데저는 평소 양말을 잘 신는편이라 평소엔 양말신고 간절기엔 덧신신으려고 합니다군더더기 없이 깔끔하고 클래식해서 맘에 듭니다이월?상품이라 제품이 100% 만족스럽진 못하지만 저렴하게 샀으니 이번엔 편하게막 신어보고 다음엔 매장에서 신제품도 구입해보고 싶네요",
            "가을에 나들이 데일리 충분했어요",
            "가볍고 데일리로 자주신을것같습니다좋습니다 화면보다 색상은 훨씬밝아요걍 베이지색으로 생걱하심 될것같아요",
            "저렴하게 구매해서 만족합니다",
            "좋아요 좋아요 좋아요 좋아요",
            "너무 마음에 들어요! 추천합니다.발볼있는 1인인데 너무 편해요.강추합니다. 단 굽이 없어 신었을 때 발모양이 예쁘진 않아요.",
            "신발잘맞고 아주 편안합니다. 까탈스런발이란 아무것나 못신는데 발편안하네요."
        ]
    },
    {
        "제품카테고리": "여성용",
        "제품명": "핏플랍 델리카토 리본 메탈릭 레더 실버 여성 발레리나 플랫슈즈_FFSO5E008SV",
        "링크": "https://prod.danawa.com/info/?pcode=88491602&cate=18242491",
        "가격": "106,470",
        "상세설명": "여성용 / 플랫 / 소재: 양가죽 / 굽 높이: 2.2cm",
        "리뷰": [
            "리뷰 없음"
        ]
    },
    {
        "제품카테고리": "구두",
        "제품명": "솔트앤초콜릿 라운드 토 스티치 레이스업 로퍼 412215009",
        "링크": "https://prod.danawa.com/info/?pcode=17291666&cate=18242491",
        "가격": "58,480",
        "상세설명": "구두 / 여성용 / 옥스퍼드 / 굽종류: 통굽(플랫폼) / 플레인토 / 소재: 인조가죽 / 총굽: 4.5cm / 색상: 블랙 / 출시가: 99,000원",
        "리뷰": [
            "리뷰 없음"
        ]
    },
    {
        "제품카테고리": "여성용",
        "제품명": "엘칸토 HC12 여성 LCWC83U43935",
        "링크": "https://prod.danawa.com/info/?pcode=64837937&cate=18242491",
        "가격": "77,420",
        "상세설명": "여성용 / 로퍼",
        "리뷰": [
            "리뷰 없음"
        ]
    },
    {
        "제품카테고리": "여성용",
        "제품명": "포멜카멜레 포멜 제니 앵클릿 로퍼 4CM FKF1F1SP011 3COLOR",
        "링크": "https://prod.danawa.com/info/?pcode=63119531&cate=18242491",
        "가격": "35,770",
        "상세설명": "여성용 / 로퍼",
        "리뷰": [
            "오랜만에 메리제인 스타일 펌프스가 신고 싶어져서 썰칭하다가찾은 건데 넘 편하고 좋으네요~가격도 착해서 살짝 러이니한 날에 신기에도 낫 밷？？",
            "가죽재질은아닌데 디자인이 신박해요",
            "디자인도 예쁘고, 편한 것 같아요~？？",
            "발이 생각보다 편해서 구입했어요~ 예뻐요"
        ]
    },
    {
        "제품카테고리": "여성용",
        "제품명": "Camper 플랫슈즈 라이트 니나 여성 발레리나 블랙_21595-242",
        "링크": "https://prod.danawa.com/info/?pcode=35310935&cate=18242491",
        "가격": "106,352",
        "상세설명": "여성용 / 플랫 / 소재: 가죽",
        "리뷰": [
            "넘 이쁘고사이즈 딱맞고 양말신고 신어도 앙징맞고 예뻐요가죽도 부드러워서 발등이랑 편하네요이신발신고 원피스 치마 청바지 다 잘어울려서 넘 예뻐요ㅎ색상 다른것도 사고 싶어요저는 대만족하고 신을겁니다",
            "착화감 굿...발레리나 슈즈 스타일의 캠퍼는맞는 사이즈가 품절였는데혹시나 발볼이 넓지 않으니사이즈를 업했는데가운데 밴딩도 있고 길이감도 편해서잘 맞아요^^ 인생 신발 득템이요...착한 가격까지~~~",
            "배송은 하루만에 왔구요! 다른곳들은 다 사이즈 품절이라 포기하려던 찰나에 드디어 여기서 구했습니다 ㅜ 매장에서 신어보고 산거라 사이즈 잘 맞아요~~ 원래 235 칼발인데 길이가 커무 딱맞아서 240 구매했습니다~ 발볼 넓은 저에겐 베스트 사이즈네용",
            "사이즈 엄청 고민했었는데 225사이즈 잘 맞아서 좋아요~칼발이라 일반구두 텐* 신으면 225도 커서 벗겨지고 맞는구두가 없어서 스트랩달린 슈즈를 찾다가 캠퍼신발을 보고 구입했는데 너무 편하고 딱맞습니다. 양말신고도 딱 쪼이지않고 정말 잘 맞아요~",
            "발볼이 많이 넓어요..구두 신기 힘든 발이예요 그런데 구두인데 부드럽고 편합니다. 만족해요",
            "정사이즈로 나와서 딱 좋아요.신으니까 착용감도 좋고 바닥이 딱딱하지 않고 쿠션도있어서 너무 좋아요.",
            "몇년 동안 신어온 신발인데 사이즈가 커졌나봐요. 항상 eu38을 신는데 좀 크네요. 양말 신고 신어야겠어요.",
            "기존에 신던 신발이 낡아서 재주문 했어요반치수 업 했는데 착화감 편해요",
            "발편한 메리제인 슈즈를 좋아하는데 정사이즈 여유 있어요 담에 재구매하고싶어요 대만족입니다 명절전인데 배송도 빨라요",
            "발도 편하고 밴드도 잘 잡아주네요 맨발로 신으면 뒤꿈치 가죽에서 물이 살짝 빠져요 별 하나 뺐어요",
            "가격도 저렴하게 잘 샀고 만족합니다.",
            "신발 편해요 추천합니다",
            "사진과 똑같고 착화감 좋아요. 편해요. 강추합니다.",
            "오른쪽 신발을 많이 신어봤는지;; 느슨해져서왼발과 오른발 차이가 좀 있네요;;반품 귀찮아서 그냥 신습니다;;",
            "소재는 고급진데 사이즈가 유럽형인지 완전 딱 맞진않아요",
            "중학생 아이 구두로 구입했어요. 약간 크게 나온듯한데, 편안해합니다",
            "가격비싼게 다 이유있어요 강추입니다 고급지고편해요",
            "250사이즈 맨발로 딱 맞아요.저는 칼발인데예쁘고 발이 작아보여요.오늘 받았는데오래 신어도 편하면 좋겠어요.",
            "신발이 편하고 발이 커보이지 않아서 좋이요",
            "가죽이 좋네요. 면세점에서 산 캠퍼랑 비교해보니 동일합니다."
        ]
    },
    {
        "제품카테고리": "여성용",
        "제품명": "바바라 소가죽 앰블럼 로퍼 _BBH542BK",
        "링크": "https://prod.danawa.com/info/?pcode=67878965&cate=18242491",
        "가격": "74,970",
        "상세설명": "여성용 / 플랫",
        "리뷰": [
            "화면으로 보기에는 발이 편해보이는데 착용하니까 가볍기는 한데 새신이라 그닥 편하지는 않아요 신어서 좀 늘어나면 괜찮을것 같아요 발볼이 좁으신 분은 정사이즈 하시면 될것 같아요디자인은 귀엽고 재질또한 좋아요 매장가서 신어보고 11번가에서 사는걸 추천합니다",
            "좋은 가격에 잘 구매했습니다. 225인데 운동화가 아니라 로퍼는 사이즈가 딱맞아야 헐떡이지않는데 이로퍼는 아주딱 맞아서 좋아요"
        ]
    },
    {
        "제품카테고리": "여성용",
        "제품명": "Camper 라이트 니나 K201365-011",
        "링크": "https://prod.danawa.com/info/?pcode=53240048&cate=18242491",
        "가격": "136,020",
        "상세설명": "여성용 / 플랫 / 메리제인 / 소재: 천연가죽",
        "리뷰": [
            "리뷰 없음"
        ]
    },
    {
        "제품카테고리": "여성용",
        "제품명": "톰맥캔 8TMOX14F1R 옥스포드 01 여성 클래식 로우 힐 로퍼 굽 2.5CM",
        "링크": "https://prod.danawa.com/info/?pcode=65457818&cate=18242491",
        "가격": "90,520",
        "상세설명": "여성용 / 플랫",
        "리뷰": [
            "고급진 가죽으로 만든 예쁜 로퍼네요.약간 무겁지만 만족합니다.",
            "여성스러운 로퍼를 찾았는데 딱 마음에 들어요. 고급스럽고 굽도 적당해서 좋아요. 올드해보이지도 않고요~"
        ]
    },
    {
        "제품카테고리": "구두",
        "제품명": "베카치노 소가죽 플랫 823003 K-040",
        "링크": "https://prod.danawa.com/info/?pcode=21531632&cate=18242491",
        "가격": "233,930",
        "상세설명": "구두 / 여성용 / 플랫 / 민자 / 소재: 천연가죽 / 총굽: 2cm / 색상: 블랙",
        "리뷰": [
            "리뷰 없음"
        ]
    },
    {
        "제품카테고리": "구두",
        "제품명": "레페토 리오 V1414V410",
        "링크": "https://prod.danawa.com/info/?pcode=5715401&cate=18242491",
        "가격": "286,329",
        "상세설명": "구두 / 여성용 / 플랫 / 민자 / 메리제인 / 소재: 천연가죽 / 에나멜 / 총굽: 1cm / 색상: 블랙 / 출시가: 458,000원",
        "리뷰": [
            "240사이즈 신는데 좀 작네요",
            "레페토 리오 디자인은 첨인데 역시나 착화감도 편하고 아주 이뻐서 넘 맘에 들어요!!"
        ]
    },
    {
        "제품카테고리": "슬리퍼",
        "제품명": "엘리자베스스튜어트 여성 양가죽 쥬얼 투웨이 슬링백 227160",
        "링크": "https://prod.danawa.com/info/?pcode=45048299&cate=18242491",
        "가격": "73,260",
        "상세설명": "슬리퍼 / 여성용 / 펌프스(미들힐) / 굽종류: 청키힐 / 소재: 천연가죽",
        "리뷰": [
            "항상 구두에 따로 쿠션깔창을 넣었는데 이건 이미 쿠션이 들어있어서 푹신하고 편해요.",
            "항상 구두에 따로 쿠션깔창을 넣었는데 이건 이미 쿠션이 들어있어서 푹신하고 편해요.",
            "이뻐요 가죽이 넘 부드러워 신으면 늘어날것같아요. 가격대비 맘에듭니다.",
            "이뻐요 가죽이 넘 부드러워 신으면 늘어날것같아요. 가격대비 맘에듭니다.",
            "배송은 느렸지만 부드럽고 맘에 듭니다.",
            "배송은 느렸지만 부드럽고 맘에 듭니다.",
            "편하게는 신겠어요.",
            "편하게는 신겠어요.",
            "발이 편하고 너무 예뻐요",
            "발이 편하고 너무 예뻐요",
            "마음에 들어요 마음에 들어요",
            "마음에 들어요 마음에 들어요",
            "예쁘당~ 신기 편하고 가죽도 부드러워서 반함",
            "엘리자베스스튜어트 뮬 샌들 잘 받았습니다.",
            "생각보다 너므 화려해요 잘신고다닐지 모르겟네요 바닥은 푹신해서 좋아요",
            "너무예뻐요.편하게 신기 좋아요",
            "발바닥부분이 푹신해서 좋네요색상은 핑크와 베이지 중간이예요",
            "넘 이뻐여 편해요",
            "발도 예뻐 보이고 편하고 좋아요",
            "신발 너무 예뻐요~^^, 바닥에 큐선도 있어서 딱딱하지도 않고, 편해요~, 평소에 240사이즈 신은데 245주문했어서 딱 좋았어요~, 배송도 주문했고 담날 오전11시쯤에 바로 받았습니다, 감사합니다~~~"
        ]
    },
    {
        "제품카테고리": "구두",
        "제품명": "미우미우 발레리나 플랫 5F653D ZHV",
        "링크": "https://prod.danawa.com/info/?pcode=18044078&cate=18242491",
        "가격": "713,500",
        "상세설명": "구두 / 여성용 / 플랫 / 민자 / 메리제인 / 소재: 천연가죽 / 총굽: 1cm / 색상: 화이트 / 출시가: 1,360,000원",
        "리뷰": [
            "발볼이 넓은편이라 평소 사이즈보다 반업해서 시켰어요. 정사이즈했으면 작았을거에요! 그리고 발등이 높아서 좀 불편하지만 참고 신을만큼 예쁘고 만족스러운 신발이에요. 롱스커트를 자주 입어서 예전부터 사고싶었는데 좋은가격에 구매할 수 있어서 바로 구매했어요.",
            "일단 정품을 확인 시켜주시는 여러 장치들이 좋았어요 계속 고민고민하다..샀는데 너무너머 예쁘네요. 구두는 보통 235 신는데..이상하게 명품 구두들은 240이 맞네요. 그래서 미우미우도 240으로 했습니다. 잘 맞습니다!^^",
            "일단 정품을 확인 시켜주시는 여러 장치들이 좋았어요 계속 고민고민하다..샀는데 너무너머 예쁘네요. 구두는 보통 235 신는데..이상하게 명품 구두들은 240이 맞네요. 그래서 미우미우도 240으로 했습니다. 잘 맞습니다!^^",
            "바닥이 얇아서 좀 아프길래 밑창보강하고 신었더니 더 편하네요",
            "예뻐요! 배송도 잘 왔구요.주문할때 사이즈 선택을 잘못 눌러서 교환하느라 시간이 좀 걸렸지만 아주 만족합니다.",
            "배송빠르고 좋아요 ㅎㅎ",
            "배송빠르고 좋아요 ㅎㅎ",
            "넘 사고싶었돈 신발 ㅎㅎ"
        ]
    },
    {
        "제품카테고리": "여성용",
        "제품명": "로저비비에 버클 트럼펫 펌프스 45mm 화이트 RVW400",
        "링크": "https://prod.danawa.com/info/?pcode=44991746&cate=18242491",
        "가격": "746,000",
        "상세설명": "여성용 / 펌프스(미들힐)",
        "리뷰": [
            "리뷰 없음"
        ]
    },
    {
        "제품카테고리": "구두",
        "제품명": "바바라 보석포인트 베이직 펌프스 BBF714BK",
        "링크": "https://prod.danawa.com/info/?pcode=18407837&cate=18242491",
        "가격": "178,300",
        "상세설명": "구두 / 여성용 / 펌프스(미들힐) / 굽종류: 청키힐 / 민자 / 메리제인 / 소재: 패브릭 / 총굽: 5cm / 색상: 블랙",
        "리뷰": [
            "리뷰 없음"
        ]
    },
    {
        "제품카테고리": "구두",
        "제품명": "페라가모 바라 젤리 발레리나 0751452",
        "링크": "https://prod.danawa.com/info/?pcode=17208575&cate=18242491",
        "가격": "274,460",
        "상세설명": "구두 / 여성용 / 플랫 / 장식 / 젤리슈즈 / 사이드오픈 / 소재: PVC / 총굽: 3cm / 색상: 핫핑크 / 출시가: 590,000원",
        "리뷰": [
            "십만원이나 더비싸게 주고 구매를 하다니 이런 왼발이 자꾸 벗겨지면 서 뒷굼치 상처 계속 쓸리고 피곤함이 심하고 넘 딱딱하고 쓸리고 헐떡거리고 미끄럽고 ㅠㅠ",
            "발에 땀나면 쓸려서 아프고 상처가 난다 왜좀더 부드럽게 못만들지",
            "빠른 배송이 마음에 듭니다.5사이즈는 작고 6은 좀 큰데역시나 크네요하지만 색은 이뻐서 좋아요스커트나 청바지 모두 무난합니다투명깔창 하나 끼우고 신으니만족합니다",
            "실버도있는데 핫핑크가 꽂힌후로계속 고민하다 구매했는데요전혀 느낌달라요대만족이에요사이즈는 정235인데 6했더니 아주 잘맞구요어떤옷이든 포인트가 되어 참 좋네요",
            "색상 완전 예뻐요~적응기간이라 뒤꿈치는 아프지만 적응하면 될것 같아요.저렴한 가격으로 예쁜 색상 구매해서 대만족~☆",
            "편해요.좀 튀는 컬러를 샀는데여름이니까 그냥 신으려구요.말랑말랑하고정사이즈 시켜도 살짝 늘어나면 커질거 같긴 해요.",
            "좋은가격에 잘 구매했어요.공주같은 느낌이랄까 암튼 예쁘게신고다녀요.추천합니다."
        ]
    },
    {
        "제품카테고리": "구두",
        "제품명": "엘리자베스스튜어트 베카새틴플랫EBAL155140",
        "링크": "https://prod.danawa.com/info/?pcode=79608911&cate=18242491",
        "가격": "55,110",
        "상세설명": "구두 / 여성용",
        "리뷰": [
            "배송도 생각보다 엄청 빠르고 화면이랑 똑같이 이쁘네요 이쁘게 잘 신을꺼 같아요 많이 파세요"
        ]
    },
    {
        "제품카테고리": "구두",
        "제품명": "세라 스틸레토 카우레더 잠자리리본 펌프스 S22P516",
        "링크": "https://prod.danawa.com/info/?pcode=31948907&cate=18242491",
        "가격": "256,910",
        "상세설명": "구두 / 여성용 / 펌프스(미들힐) / 굽종류: 스틸레토힐 / 장식 / 소재: 천연가죽 / 총굽: 6cm / 색상: 아이보리, 블랙",
        "리뷰": [
            "디자인이 이뻐요 이 브렌드 자체가 발복이 좁은 것 같아요. 사이즈도 다른 브렌드에 비해 작고..한치수 크게 주문하셔야 성공할 것 같습니다.",
            "예쁘게 잘 신고 있습니다다들 예쁘다고하네요"
        ]
    },
    {
        "제품카테고리": "구두",
        "제품명": "로저비비에 버클 레더 트럼펫 펌프스 RVW40015280 D1P B999",
        "링크": "https://prod.danawa.com/info/?pcode=15199883&cate=18242491",
        "가격": "719,118",
        "상세설명": "구두 / 여성용 / 펌프스(하이힐) / 굽종류: 스틸레토힐 / 장식 / 소재: 천연가죽 / 에나멜 / 총굽: 7cm / 색상: 블랙 / 출시가: 1,050,000원",
        "리뷰": [
            "정성스러운 포장과 메모감사드립니다. 명함이 동봉되어 있다고 하셨는데 명함은 누락된 것 같아요^^;; 저는 로저 트럼펫 4.5cm가 착화감이 너무 좋아서 하루종일 신을 수 있고 달리기도 할 수 있어요;; 그래서 이번에는 7cm로 도전합니다. 7cm도 역시나 편해요. 국내구두 225신는데 로저는 34가 잘 맞아요. 사이즈를 아니까 인터넷에서 구매가능하니 편하네요!",
            "정성스러운 포장과 메모감사드립니다. 명함이 동봉되어 있다고 하셨는데 명함은 누락된 것 같아요^^;; 저는 로저 트럼펫 4.5cm가 착화감이 너무 좋아서 하루종일 신을 수 있고 달리기도 할 수 있어요;; 그래서 이번에는 7cm로 도전합니다. 7cm도 역시나 편해요. 국내구두 225신는데 로저는 34가 잘 맞아요. 사이즈를 아니까 인터넷에서 구매가능하니 편하네요!",
            "페라가모 37 보다는 조금 큰 느낌이에요 운동하고 약간 발이 부은 상태인데도 헐렁하게 맞네요 신발 너무 이뿌네요. 반사이즈 작게했어도 됐을듯",
            "페라가모 37 보다는 조금 큰 느낌이에요 운동하고 약간 발이 부은 상태인데도 헐렁하게 맞네요 신발 너무 이뿌네요. 반사이즈 작게했어도 됐을듯",
            "진짜 너무 예뻐요. 선물포장부탁드렸는데 예쁘게 왔어요. 저는 발볼이 넓은 240이라 크다는 의견이 많은데도 37로 했는데 편안하게 맞아서 37로 하길 잘한 것 같아요.",
            "진짜 너무 예뻐요. 선물포장부탁드렸는데 예쁘게 왔어요. 저는 발볼이 넓은 240이라 크다는 의견이 많은데도 37로 했는데 편안하게 맞아서 37로 하길 잘한 것 같아요.",
            "배송이빠르고 포장도 좋고 상품도 깔끔하고 문의도 답변잘해주시고 더많은 상품올려주심 좋게써요 사이즈아니까 백화점 안가도되고 조아요",
            "예쁘게 잘 신을게요",
            "예쁘게 잘 신을게요",
            "저렴하게 잘 구매했어요",
            "시간은 오래 걸렸지만 저렴하게 구입해서 만족해요",
            "시간은 오래 걸렸지만 저렴하게 구입해서 만족해요",
            "사이즈가 살짝 큰데 칼창 깔면 괜찮을 것 같아여 만족",
            "고민하다 35로 선했어요.집에 오자마자 신어보고 예쁘고 잘 샀어요.",
            "쓱 배송 최고에요! 점심쯤 주문했더니 다음을 바로 오네요ㅎㅎ 급하게 필요할때 주문하기 좋겠어요ㅎㅎ 평소 운동화는 220 신고 구두는 발볼이 넓어서 230 신어요. 매장 가서 신어봤는데 35는 너무 딱 맞고 36은 커서 35.5 신어보니 딱 좋더라구요. 매장 직원분은 앞에 깔창 깔면 되겠다고 하셨는데 원래 구두를 여유있게 신는 편이라 그냥 신어도 괜찮을 거 같아요! 매장가 110인데 쿠폰 쓰고 카드사 할인까지해서 90좀 안되게 샀네요>< 완전 이득!!! 쇼핑백이 없는게 좀 아쉽긴 한데 꼭 필요한건 아니니까요ㅎㅎ 여유 굽까지 챙겨줘서 넘 좋아요~~ 좋은 구두 하나 사야지 했을 때 바로 떠오른 로저비비에ㅎㅎ 색상 고민 했는데 검정 사길 잘 한 거 같아요ㅎㅎ 여기저기 정말 잘 신을 듯!!! 보니까 매장에서 구매하면 미끄럼방지 스티터 붙여주는 거 같던데 저는 얼른 밑창보강 해야겠어요ㅋㅋ 유광이라 손 지문자국이 많이 남는데 잘 닦아주면서 신으려구요ㅎㅎ 보고만 있어도 기분이 좋아지는 구두ㅎㅎ 내년 경조사를 잘 부탁해~!!",
            "쓱 배송 최고에요! 점심쯤 주문했더니 다음을 바로 오네요ㅎㅎ 급하게 필요할때 주문하기 좋겠어요ㅎㅎ 평소 운동화는 220 신고 구두는 발볼이 넓어서 230 신어요. 매장 가서 신어봤는데 35는 너무 딱 맞고 36은 커서 35.5 신어보니 딱 좋더라구요. 매장 직원분은 앞에 깔창 깔면 되겠다고 하셨는데 원래 구두를 여유있게 신는 편이라 그냥 신어도 괜찮을 거 같아요! 매장가 110인데 쿠폰 쓰고 카드사 할인까지해서 90좀 안되게 샀네요>< 완전 이득!!! 쇼핑백이 없는게 좀 아쉽긴 한데 꼭 필요한건 아니니까요ㅎㅎ 여유 굽까지 챙겨줘서 넘 좋아요~~ 좋은 구두 하나 사야지 했을 때 바로 떠오른 로저비비에ㅎㅎ 색상 고민 했는데 검정 사길 잘 한 거 같아요ㅎㅎ 여기저기 정말 잘 신을 듯!!! 보니까 매장에서 구매하면 미끄럼방지 스티터 붙여주는 거 같던데 저는 얼른 밑창보강 해야겠어요ㅋㅋ 유광이라 손 지문자국이 많이 남는데 잘 닦아주면서 신으려구요ㅎㅎ 보고만 있어도 기분이 좋아지는 구두ㅎㅎ 내년 경조사를 잘 부탁해~!!",
            "쓱 배송 최고에요! 점심쯤 주문했더니 다음을 바로 오네요ㅎㅎ 급하게 필요할때 주문하기 좋겠어요ㅎㅎ 평소 운동화는 220 신고 구두는 발볼이 넓어서 230 신어요. 매장 가서 신어봤는데 35는 너무 딱 맞고 36은 커서 35.5 신어보니 딱 좋더라구요. 매장 직원분은 앞에 깔창 깔면 되겠다고 하셨는데 원래 구두를 여유있게 신는 편이라 그냥 신어도 괜찮을 거 같아요! 매장가 110인데 쿠폰 쓰고 카드사 할인까지해서 90좀 안되게 샀네요>< 완전 이득!!! 쇼핑백이 없는게 좀 아쉽긴 한데 꼭 필요한건 아니니까요ㅎㅎ 여유 굽까지 챙겨줘서 넘 좋아요~~ 좋은 구두 하나 사야지 했을 때 바로 떠오른 로저비비에ㅎㅎ 색상 고민 했는데 검정 사길 잘 한 거 같아요ㅎㅎ 여기저기 정말 잘 신을 듯!!! 보니까 매장에서 구매하면 미끄럼방지 스티터 붙여주는 거 같던데 저는 얼른 밑창보강 해야겠어요ㅋㅋ 유광이라 손 지문자국이 많이 남는데 잘 닦아주면서 신으려구요ㅎㅎ 보고만 있어도 기분이 좋아지는 구두ㅎㅎ 내년 경조사를 잘 부탁해~!!",
            "쓱 배송 최고에요! 점심쯤 주문했더니 다음을 바로 오네요ㅎㅎ 급하게 필요할때 주문하기 좋겠어요ㅎㅎ 평소 운동화는 220 신고 구두는 발볼이 넓어서 230 신어요. 매장 가서 신어봤는데 35는 너무 딱 맞고 36은 커서 35.5 신어보니 딱 좋더라구요. 매장 직원분은 앞에 깔창 깔면 되겠다고 하셨는데 원래 구두를 여유있게 신는 편이라 그냥 신어도 괜찮을 거 같아요! 매장가 110인데 쿠폰 쓰고 카드사 할인까지해서 90좀 안되게 샀네요>< 완전 이득!!! 쇼핑백이 없는게 좀 아쉽긴 한데 꼭 필요한건 아니니까요ㅎㅎ 여유 굽까지 챙겨줘서 넘 좋아요~~ 좋은 구두 하나 사야지 했을 때 바로 떠오른 로저비비에ㅎㅎ 색상 고민 했는데 검정 사길 잘 한 거 같아요ㅎㅎ 여기저기 정말 잘 신을 듯!!! 보니까 매장에서 구매하면 미끄럼방지 스티터 붙여주는 거 같던데 저는 얼른 밑창보강 해야겠어요ㅋㅋ 유광이라 손 지문자국이 많이 남는데 잘 닦아주면서 신으려구요ㅎㅎ 보고만 있어도 기분이 좋아지는 구두ㅎㅎ 내년 경조사를 잘 부탁해~!!",
            "너무 영롱하네요 예쁘고 편하고 최고입니다 또 구매하러 올게요! 포장 배송 상태 모두 마음에 듭니다! 배송도 빠르고요",
            "포장 꼼꼼하게 바로ㅈ배송으로 보내주셨어요 235정 사이즈인데 36사이즈가 딱 잘 맞네요 발도 안아프고 좋아요"
        ]
    },
    {
        "제품카테고리": "구두",
        "제품명": "페라가모 바라 젤리 발레리나 0726366",
        "링크": "https://prod.danawa.com/info/?pcode=14818019&cate=18242491",
        "가격": "341,486",
        "상세설명": "구두 / 여성용 / 플랫 / 장식 / 젤리슈즈 / 사이드오픈 / 소재: PVC / 총굽: 3cm / 색상: 실버 / 출시가: 590,000원",
        "리뷰": [
            "배송도 빠르고 포장도 꼼꼼하게 잘 왔어요. 페라가모 젤리슈즈 3켤레째입니다. 신발은 예쁜데, 몇번 신지 않았는데 끊어졌어요.. 여름에는 이만한 신발이 없어서 약한 거 알면서도 또 사게 되는 신발.. 입니다. ;",
            "사이즈 때문에 고민이 많았는데제품상세페이지에 있는 사이즈표대로 구매하면 됩니다신발 너무 이쁘고 편해서 맘에 듭니다",
            "이쁘고 편해요 실버 플랫 좋아하는데 젤리슈즈지만 고급스러워보이고 구두 굽 뒤가 은근 화려하네요~~",
            "착한가격에 너무너무 예쁜신발 구매했네요 검정보다 더 마음에 드네요 goodgoodgood",
            "신발은 예쁜데 뒤꿈치 아파요ㅠ 아쉽네요",
            "신발은 예쁜데 뒤꿈치 아파요ㅠ 아쉽네요",
            "오 ~ 너무 이뻐요~~다른색상도 구매하고 싶네요~",
            "배송빠르고 상품도 맘에 들어요^^250에 8사이즈 딱이네요",
            "너무 마음에 들어요! 추천합니다.",
            "너무 마음에 들어요! 추천합니다.",
            "좋은 가격에 잘 구매했습니다.",
            "빠른 배송이 마음에 듭니다.생각만큼맘에들지는않네요가컥에비해실망스럽네요반품못한게후회제품",
            "빠른 배송이 마음에 듭니다.",
            "볼 넓은 245인데요..8사이즈 하니 아주 편하게 잘 맞았어요.245~250신으시면 8사이즈 잘 맞아요. 7했으면 작았을것 같아요. 사진보다 실물이 더 탄탄하고 예뻐요. 사진상으로는 옆부분 고무가 약해보여서 걱정했는데... 받아보니 괜찮았어요. 사진도 같이 올리긴 하는데 사진이랑 실제는 완잔 틀려요. 사진이 예쁘게 안 담아지네요. 아주 편해요. 불편한신발 못신으시면 완전 강추입니다.",
            "블랙 구매하고 하나더 구매했네요..올 여름 슈즈로 페레가모 잴리슈즈 두켤레면 거뜬히 날수 있겠어요..좋은가격에 빠른배송에 품질과 디자인까지..매우만족합니다..235사이즈인데 6사이즈 잘맞아요",
            "사이즈는 발볼때문에. 발볼맞혀서 구매했는데. 약간에 크기는 조금있네요~ 색상과 모든면에서는. 사진과 동일합니다~~ 이뿌네요~ 잘받았습니다.....",
            "진품 맞는거 같네요 늘 백화점 매장에서 사다가 첨 사봤는데.. ssg보증이란말에 믿고시켜봤네요 235사이즈 잘맞는편인데 딱입니다 너무 조이는 고무느낌이아니라 편하네유 찰떡!!!!",
            "넘넘 예뻐요250 사이즈 신는데 8 사이즈 아주 좋아요좋은 상품 좋은 배송 좋은 가격 삼박의 만족으로쌈바춤이 절로 나옵니닷쌈바쌈바쌈바싸바",
            "너무 마음에 들어요! 추천합니다.포장 뜯는 순간 상자부터가 감동이었어요예뻐요!반치수 덜되게 작아요 반사이즈 업하시는거 추천해요",
            "발볼이 없는 250인데 8사이즈 여유있게 잘 맞습니다. 가격도 빠른 배송도 전부 마음에 듭니다. 덕분에 잘 신겠습니다."
        ]
    },
    {
        "제품카테고리": "여성용",
        "제품명": "로저비비에 여성 메탈 버클 트럼펫 펌프스 70mm 블랙 RVW40015280 NK0 B999",
        "링크": "https://prod.danawa.com/info/?pcode=59945285&cate=18242491",
        "가격": "679,470",
        "상세설명": "여성용 / 펌프스(미들힐)",
        "리뷰": [
            "리뷰 없음"
        ]
    },
    {
        "제품카테고리": "여성용",
        "제품명": "더말랑 민자 천연소가죽 펀칭플랫슈즈 17247405 01_SD-1724 블랙 225",
        "링크": "https://prod.danawa.com/info/?pcode=45099647&cate=18242491",
        "가격": "19,800",
        "상세설명": "여성용 / 플랫",
        "리뷰": [
            "리뷰 없음"
        ]
    },
    {
        "제품카테고리": "여성용",
        "제품명": "엘리시아 페니 ELISEA RW0061",
        "링크": "https://prod.danawa.com/info/?pcode=67380851&cate=18242491",
        "가격": "108,920",
        "상세설명": "여성용 / 로퍼",
        "리뷰": [
            "푹신하고 좋습니다 발볼폭도 보통 정사이즈입니다 고급스럽습니다",
            "바닥도 푹신하고 사진보다 연한 색상으로 더 이뻐요",
            "발볼이 넓어서 조끔 끼는데 늘어나겠죠..?색도 예쁘고 쿠션감도 좋아요! 보는 사람마다 예쁘다고 하네요 ㅎ"
        ]
    },
    {
        "제품카테고리": "여성용",
        "제품명": "미우미우 힐 펌프스 5I013EFM055055 F0002 BLACK",
        "링크": "https://prod.danawa.com/info/?pcode=53437940&cate=18242491",
        "가격": "1,072,700",
        "상세설명": "여성용 / 펌프스(미들힐)",
        "리뷰": [
            "리뷰 없음"
        ]
    },
    {
        "제품카테고리": "구두",
        "제품명": "르느와르 쿠션 로퍼 펌프스 RENPUC3805K1",
        "링크": "https://prod.danawa.com/info/?pcode=31408676&cate=18242491",
        "가격": "212,610",
        "상세설명": "구두 / 여성용 / 체인로퍼(장식) / 굽종류: 청키힐 / U팁 / 소재: 천연가죽 / 총굽: 4cm / 색상: 블랙",
        "리뷰": [
            "리뷰 없음"
        ]
    },
    {
        "제품카테고리": "구두",
        "제품명": "엘리자벳 쉬크라인힐 E7270",
        "링크": "https://prod.danawa.com/info/?pcode=1782601&cate=18242491",
        "가격": "75,100",
        "상세설명": "구두 / 여성용 / 펌프스(하이힐) / 굽종류: 스틸레토힐 / 민자 / 소재: 천연가죽 / 에나멜 / 총굽: 7,8,9cm / 색상: 연핑크, 바닐라, 버건디, 베이지, 네이비, 초코, 블랙A, 블랙B, 와인, 스킨핑크, 핑크 / 출시 사이즈: 220~255mm",
        "리뷰": [
            "이게 발볼 넓힌건가요?전혀 아닌거 같은데요.다들 리뷰에 사이즈가 커다고해서 딱 맞게235로 시켰는데 발에도 너무 딱 맞아 금세 발 아플것같고, 발볼도 전혀 넓힌거 같지 않아요.사이즈만 맞음 신발은 참 이쁩니다.제조사와 통화 해 보고 싶어요.",
            "작년에 여기서 그레이 구두를 샀었는데 굽이 높은편인데도 발이 편해서 제작이라 시간이 걸리는데도 다시 블랙색상으로 재구매했어요 역시 이쁘고 발도 편하네요 안내주신 날짜보다 배송이 빨리와서 기분이 너무 좋아요 블랙스커트나 청바지에 신어도 너무 예뻐요^^",
            "밝은 핑크가 필요해서 주문을 했는대 주황색 힐이 왔어요 머드핑크 라고 하더라구요. 예쁜데 자신이 없어서 교환하려다 이제 봄도 다가와 교환취소하고 신으려구요. 그리고 연핑크 다시 주문 합니다.색상 이름 잘 확인 하고 주문하세요 저처럼 실수하지 마시고그래도 발이 편하고 예뻐 저에게 선물줬다 생각 할려고 합니다.",
            "신발이 왜이리 큰가요맞춤제작인데 기본틀이 있을건데요이브랜드는 이사이즈가 아닌데요이상합니다그리고 바닥이 너무 저럼해보여요고급진거로 붙이면 좀 좋을거같아요혹시 깔창종 보내주실순 없나요?맞춤이라 오래걸렸습니다참고하세요",
            "색상 선택을 잘못해서..제 잘못이라..엘리자벳 구두 정말편합니다.새신발인데도 늘 신던신발처럼이요~~다른색도 주문해야겠어요",
            "엘리자벳 구두는 많이 신었는데이신발은 예쁜건 포기한 디자인?그러나 발은 정말 편합니다발편한구두 찾으시는분이라면백퍼만족하실거예요",
            "기본 스타일의 정장 구두입니다. 정사이즈이고발이 편해요. 굽라인이 예쁜 신발입니다.",
            "워낙 엘리자벳 구두만 주문해서 신어봐서 좋은건 말해 뭐해요^^ 착화감 좋고 오래 신고 다녀도 발이 아프지 않아요. 근데 이번 구두는 크게 나온듯 해요",
            "후기가 좋아서 너무 기대한걸까요?실망이예요 주문제작이라고 해서 발에 잘 맞을줄알았으나 정사이즈에서 한치수 작게주문 했는데도 크고 앞코는 쓸데없이 길어서 스타일도안살고 라이트그레이라더니 그냥그레이고 어디하나. 맘에드는 구석이없네요 돈버린거같아요ㅜㅜ",
            "가성비 좋아종종 구매합니다구두 235.운동화240 신는데요235사이즈 오후에 발부어도 편하게 잘맞는거보니 약간 여유있게나온거같아요 그래서 만족스러워요",
            "한사이즈 다운했어요높은 구두 오랜만에 신는데 불편함없이 신어요^^",
            "볼이 넓어 걱정했는데 잘맞고 연핑크 색상 너무 이뻐요. 불편감이 하나도 없어요",
            "253쯤 되는 발이라 255구매했습니다.굽 모양이 이쁘고 착화감도 좋습니다.앞코가 긴편이니 싫으신 분들은 다른 걸로 주문하세요~",
            "사이즈가 크게 나왔다고 해서평소 230을 225로 주문발볼이 없어서인지 그래도 살짜커서 얇은 깔창 넣고 신우니딱 맞아요~",
            "맞춤 신발이라 어쩔수 없이 반품은 못하고...ㅠ걸을때마다 뽀드득뽀드득 소리가 나요.소리가 너무 거슬려 신고 다니지 못하겠어요.그리고 힐쪽이 너무 뾰족해서 좀 불안해요.편하다고 해서 기대했었는데...역시나네요...",
            "좋은제품 합리적인.가격에 만족합니다10년전 엘리자벳 신기시작해 쭈~욱 만족이요",
            "생각보다 살짝 아주 살짝 커서 헐거운 부분이 있어요제가 발볼이 넓은편인데도 살짝 큰 부분이 있네요~스타일은 올드해보이는 기본 입니다",
            "좋은제품입니다칼라별 장착완료.어떤옷에도 잘 어울리고 오래 신어도 불편하지 않아요추천합니다",
            "핑크색이 오렌지빛이 납니다깜짝놀랐지만, 착용감편하고 신으니, 검은피부와ㅜㅜ 잘어울려버리네요ㅜㅜ그래서 반품안하고 다시 연핑크로 재주문했어요",
            "저의 신발장에 있는 힐은 거의 여기 제품일정도로 애용하는 곳인데 이번 구두는 좀 크네요.보행하다 벗겨질까 조금 걱정 되네요.디자인은 나무랄데가 없는데 제 발이 작아졌을리는 없는데 말이죠"
        ]
    },
    {
        "제품카테고리": "여성용",
        "제품명": "라코스테 111164 토오픈힐 하이힐 봄여름 킬힐 신발 12cm나이트",
        "링크": "https://prod.danawa.com/info/?pcode=45010607&cate=18242491",
        "가격": "39,300",
        "상세설명": "여성용 / 펌프스(미들힐) / 펌프스(하이힐)",
        "리뷰": [
            "리뷰 없음"
        ]
    },
    {
        "제품카테고리": "구두",
        "제품명": "핏플랍 알레그로 레더 페니 로퍼 FFSO3E024W1",
        "링크": "https://prod.danawa.com/info/?pcode=19689947&cate=18242491",
        "가격": "48,910",
        "상세설명": "구두 / 여성용 / 페니로퍼 / U팁 / 소재: 천연가죽 / 총굽: 3cm / 색상: 라이트브라운 / 출시가: 209,000원",
        "리뷰": [
            "평소보다 한사이즈 업에서 사이즈 클줄 알았는데 고무밴딩이라 아주 편하게 신고 있어요 너무 편하고 좋네요 핏플랍 다른 신발도 사려구요 좋은 제품 득템해서 아주 좋네요",
            "좋은 가격에 잘 구매했습니다.핍플랍은 샌들만 신었었늣데로퍼도 편하네요가볍고 쿠션감있는 편한 신발이네요!!!!!",
            "예전부터 장바구니에 담아놓은 건데 가격이 다운되어 얼른구매해봅니다 고무가 부드럽고 바닥이 쿠션감이 있어 발이 편합니다",
            "신발은 한사이즈 크게 주문했더니 편하고 이쁘네요",
            "좋은 가격에 잘 구매했습니다. 예쁘고 귀여운면도 있습니다. 플랫슈즈처럼 보이지만 안쪽으로 굽이 있어서 신고 걷기 편합니다.",
            "크기는 맞은데 앞으로 약간 쏠리네요.신다보면 좋아지겠죠",
            "좋아요 맘에 들어요 잘 사용할 수 있을듯해요",
            "정사이즈 입니다,발이 들어가면 너무 편안합니다.늘어나도 잘 잡아줄듯 뒤끔치가 헐떡거리지 않을듯 함",
            "사이즈 좀 작게 나왔네요. 한 치수 크게 주문하세요. 디자인은 생각보다 올드한데 가죽 상태는 좋아요",
            "지인의 소개로 편하다고 해서 구매 할인도 많이하고 포인트까지 최저가로 샀네요 발등이 깔끔하지 않지만 신다보면 별거아니니까",
            "정사이즈로 발에 잘 맞고 색상도 화면과 같아요 발이 불편하지 않고 편안해요~",
            "신발이 가볍고 신고벗기가 편하고 좋아요",
            "잘받았습니다 빠른배송 감사합니다 임신하고 편한신발 찾고있는데 추천받아서 구매했습니다 너무 편해요",
            "신었을 때 넘 편안하고 좋아요디자인도 맘에 들어요",
            "너무 마음에 들어요! 추천합니다."
        ]
    },
    {
        "제품카테고리": "여성용",
        "제품명": "제옥스 여성신발 코스모폴리스 플러스 그립 모카신 W1S35RC3S31",
        "링크": "https://prod.danawa.com/info/?pcode=49582304&cate=18242491",
        "가격": "65,510",
        "상세설명": "여성용 / 플랫",
        "리뷰": [
            "발바닥이 다른제품에 비해서 통풍이 잘되는 디자인이라서통풍이 잘되어 좋을듯합니다",
            "빠른배송 감사합니다 맘에 들어요"
        ]
    },
    {
        "제품카테고리": "구두",
        "제품명": "누오보 무아르 1.5 NC30452 (블랙)",
        "링크": "https://prod.danawa.com/info/?pcode=19100105&cate=18242491",
        "가격": "40,401",
        "상세설명": "구두 / 여성용 / 로퍼 / U팁 / 소재: 인조가죽 / 총굽: 1.5cm / 색상: 블랙",
        "리뷰": [
            "누오보 만족합니다.발 볼이 있는지라 한치수 크게 신어봐요. 편하게 신을것 같아요.",
            "착용감좋아요. 가벼워요",
            "매장에서 신어보고 산건데도 조금크게나온듯해요가벼워요",
            "가죽이 아니지만 재질이 부드러워요. 바닥이 얇아서 불편할 줄 알았는데 신어보니 얇아도 괜찮네요. 편해서 지인에게도 권하고 저는 2번째 구입해서 신고 있어요.",
            "가죽이 아니지만 재질이 아주 부드러워요. 30만원짜리 구두보다 편해서 3번째 구입했어요.",
            "하나신었는데 발이 넘 편해서 하나 더 구입",
            "잘받았습니다~아주좋아요",
            "신발 편해요. 저렴하게 잘 샀어요.",
            "에비씨마트보다 여기가 더 저렴",
            "좋아요~",
            "푹신푹신하고 좋아요잘 신을게요",
            "편하고 좋아요!!!",
            "높은 굽 못시는 사람에게 강추합니다굽이 그래도 조금은 더 있었으면 좋겠어요너무 낮아서 발에 피로감이 있어요구두 앞코도 넉넉한 편이라서 신을 때도 편하고 착용감은 좋아요",
            "심플하고 바닥이 푹신해서 좋아요. 양말신고 신어도 잘맞아요. 정사이즈인듯합니다.",
            "신발 잘 맞고 편하고 좋네요. 위메프 통해 좋은신발 좋은 가격으로 잘 구매했어요. 번창하세요~^^"
        ]
    },
    {
        "제품카테고리": "구두",
        "제품명": "바이네르 컴포트 펌프스 379D",
        "링크": "https://prod.danawa.com/info/?pcode=33427676&cate=18242491",
        "가격": "199,610",
        "상세설명": "구두 / 여성용 / 펌프스(미들힐) / 굽종류: 스틸레토힐 / 장식 / 소재: 천연가죽 / 총굽: 4cm / 색상: 블랙",
        "리뷰": [
            "리뷰 없음"
        ]
    },
    {
        "제품카테고리": "구두",
        "제품명": "탠디 펌프스 J1430 LA-087",
        "링크": "https://prod.danawa.com/info/?pcode=7910770&cate=18242491",
        "가격": "87,140",
        "상세설명": "구두 / 여성용 / 펌프스(미들힐) / 굽종류: 청키힐 / 민자 / 소재: 천연가죽 / 총굽: 5cm / 색상: 블랙",
        "리뷰": [
            "리뷰가 좋아 믿고 구매했어요. 요즘 백화점 구두 가격 너무 비싸요…ㅠ 칼발이고 신발 잘못 사면 정말 고생하는데 너무 편해요. 통굽이라 안정적이고 굽 스크래치도 상대적으로는 덜 날 것 같아오. 같은 구두로 베이지 버건디 네이비 등등 나와도 참 좋겠어요.",
            "발볼이 많이 좁네요 신발안 쿠션이 이상하게 대어져 마무리된것 같아요 앞 부분이 불편합니다",
            "발볼이 많이 좁네요 신발안 쿠션이 이상하게 대어져 마무리된것 같아요 앞 부분이 불편합니다",
            "디자인은 딱 기본템이여서 어떤옷에도.무난하고 무엇다보다 발이 정말 편해요",
            "신발 진짜 편하고 좋네요",
            "작게 나온거 같아서 맘에 드네요. 심플하고 단정합니다.",
            "작게 나온거 같아서 맘에 드네요. 심플하고 단정합니다.",
            "디자인 예쁘고 편하고 좋아요",
            "저렴하고 편한데이젠 춥네요 ㄷㄷㄷ잘신고잇ㅇ습니당",
            "나쁘지 않아요 근데 살짝 큰거같네요 배송도 빠르지 않았어요",
            "나쁘지 않아요 근데 살짝 큰거같네요 배송도 빠르지 않았어요",
            "신으닌까 이쁘네요잘 신을께요",
            "사이즈도 잘 맞고 예뻐요",
            "좋은 가격에 잘 구매했습니다.",
            "굽이 넓어서 편해요",
            "상품 품질이 좋습니다. 마음에 들어요! 문안하게 신을수있는 검정구두를 찾고 있었는데 딱 안성맞춤입니다. 격식을 차리는 자리나 좀 편안한자리에 모두 어울립니다",
            "디자인과 가죽은 좋아요.다만 발볼이 좁게 나왔네요.",
            "목빠지게 기다리다 오늘 드뎌 받았습니다. 선물포장부터 정성스럽게 해주셔서 감동이었어요. 여분깔창도 넣어주시고 너무 좋아요. 타임스퀘어 남자직원분 너무 친절하게 잘 대해주세요. 남편꺼 사러 갈께요. 신발 너무 이쁘고 좀 기다렸어도 포장 뜯어보면서 다 풀렸어요. 첫조카 돌에 신을 마땅한 신발이 없어서 급하게 주문했는데 맘에 쏙듭니다. 감사합니다~^^",
            "진짜 앞부분이 조금만 길었으면 하는 아쉬움...바닥부분 푹신하고 부드러워요.",
            "발등을 좀 더 덮었으면 좋겠다는 후기가 실물을 보니 이해되네여. 그래도 8만원에 구입한것 치고 가격메리트가 있어 만족합니다. 배송이 3~4일 걸렸어요. 그래도 굽이 많이 높지 않고 기본 스탈에 가격, 브랜드 만족해서 별5개 입니다"
        ]
    },
    {
        "제품카테고리": "구두",
        "제품명": "엘리자벳 클린 오픈힐 EL16140 (7cm)",
        "링크": "https://prod.danawa.com/info/?pcode=3898619&cate=18242491",
        "가격": "80,230",
        "상세설명": "구두 / 여성용 / 펌프스(하이힐) / 굽종류: 스틸레토힐 / 민자 / 토오픈+사이드오픈 / 소재: 천연가죽 / 에나멜 / 총굽: 7cm / 색상: 블랙, 네이비, 아이보리 / 출시 사이즈: 220~255mm",
        "리뷰": [
            "신발 예뻐요. 감사 합니다. 신발이 잘 맞아요. 걷기 편 하고 너무 좋네요. 감사 합니다. 예뻐요. 달콤 달콤 새콤새콤",
            "신발 예뻐요. 감사 합니다. 예쁜 신발 감사 합니다. 톡톡 톡톡 한 하루 되세요.",
            "하얀 겨울 처럼 예쁜 구두 토 오픈 슈즈 감사 합니다. 전체적으로 편안 하고 너무 너무 발랄 해요. 감사 합니다.",
            "신발 예뻐요. 색감도 예쁘고 화사 하고 너무 좋아요. 신어 봤는데, 너무 좋아요. 감사 합니다.",
            "토 오픈 8cm 구두 아름답습니다. 감사 합니다. 아름다운 시간 되세요.",
            "토 오픈 슈즈 높고 예뻐요날씬 하고 깨끗 해요톡톡 하죠감사 합니다",
            "뾰족~~~하니아주좋네용ㅋ 잘신을께요 편해서 좋아용ㅎㅎㅎ",
            "상품 준비가 늦어져서 배송이 늦게 된거 빼고는 디자인이나 색상 다 맘에 들어요. 가볍고 편하고.. 색상은 짙은 네이비 인줄 알았는데 초록색이네요. 그래도 특이하고 이뻐요. 초록색 신발은 처음인데 색상 이쁘네요. 잘 신을께요.",
            "대부분의 신발을 인터넷으로 구매하고 사이즈 틀린적이 없었는데 이 구두는 작음 그래서 발이 매우 아픔 ㅡㅡ",
            "평소 235 볼 넓은편인데요 딱 맞게 신으려고 정사이즈 구매했어요~ 헐떡이지 않고 좋아요 디자인도 색상도 예쁩니다 발볼이 없으면 한치수 다운해도 좋을듯 하네요",
            "주문한 사이즈 8cm 굽 잘 받았습니다 착용감 좋아요",
            "맘에들어요블루도기다려줘용",
            "토오픈 아닌 일반 구두는 240, 운동화는 245 신는데 이건 240 주문했는데 넘넘 커요. 막 벗겨져요. 한 번 밖에 안, 아니 못 신었는데 깔창 몇개 깔아서신어 봐야 할 듯요ㅜㅜ",
            "사이즈가 작아서 잘 못 신겠어요",
            "다른 신발보다는 신어보고살것 하는 후회가 된는 신발이에요. 약간 불편하고 신기도 쉽지 않네요.",
            "엘리자벳구두는 올해만 전 벌써 5켤레 구입했어요 높은힐부터 낮은굽까지 디자인부터 소재 다 만족스러웠어요 그리구 우선 발이 너무편해서 너무 좋아요~^^",
            "구두 와서 신고 아파트 1층 내려갔다가 이꼴 됐습니다. 사람 발목 부러지라고 만든 신발인가요? 어떻게 이렇게 만들어서 보냅니까?",
            "이뻐요~~~색상이 사진보다는 덜이뻐요 발은 편하네요",
            "엄지발가락을 눌러 아프네요ㅠ",
            "다른 신발보다 좀 큰거 같지만 예쁘네요"
        ]
    },
    {
        "제품카테고리": "여성용",
        "제품명": "소다 소다 여성세미드레스 펌프스 ALF939LH32 베이지 7CM",
        "링크": "https://prod.danawa.com/info/?pcode=45177311&cate=18242491",
        "가격": "167,140",
        "상세설명": "여성용 / 펌프스(미들힐)",
        "리뷰": [
            "너무 마음에 들어요! 추천합니다."
        ]
    },
    {
        "제품카테고리": "여성용",
        "제품명": "엘칸토 인텐스 여성 플랫 메리제인_LCWD87I513",
        "링크": "https://prod.danawa.com/info/?pcode=75135773&cate=18242491",
        "가격": "36,000",
        "상세설명": "여성용 / 플랫 / 메리제인 / 소재: 인조가죽 / 굽 높이: 2cm",
        "리뷰": [
            "신발이 한싸이즈 크게 나오긴했어요235를 샀어야 할걸 ..ㅜ다이소에서 발꿈치 패드사서 붙이고 신어요발볼은 편합니다",
            "낮은굽이고 한사이즈 업한거라 여유있고 편합니다. 그래도 새구두라 그런지 뒷목이 쓸려서 살짝 까졌네요. 밴드 붙이고.. 잘. 신고 다닙니다",
            "가격도 저렴하고 모양도 예쁩니다.볼크기가 적당해서 발이편합니다.",
            "편하게 잘 신고 있습니다. 근데 장시간 신으면 발가락이 좀 아프네요",
            "검정색 샀는데 발이 편하여 베이지도 구매했어요",
            "배송하루늦었네요 사이즈는정사이즈고 폭신폭신좋아요 좋아요",
            "첨엔 발볼이 좁아서 않신고 다니다가 계속 신어보니넓어지더라구요",
            "모양도 이쁘고 발이.넘 편해요",
            "디자인도 예쁘고 괜찮아요",
            "사이즈가 넉넉한 편이고 굽이 적당합니다누드톤이라 받쳐 신기도 좋아요",
            "나이가 들어 그런지 발볼이 더 넓어진듯해요 전에 235을 주문했다가 너무 꼭 맞아서 다른 사람 주었는데 한 사이즈 올려 주문했더니 약간 커서 헐떡임이 있어 앞쪽의 끈을 조절하니 조금 나은듯 했는데 뒷꿈치도 많이 벗겨져서 통증이...ㅠ.ㅠ ...그래도 디자인이 이뻐서 잘 길들여 신어보려 합니다. 빠른 배송 감사합니다^^",
            "친정엄마 선물로 사드렸는데 가벼워서 좋긴한데 볼이 좁다고 불편해 하세요ㅜㅜ",
            "간단히 신어보았는데 발은편할것같고 디자인도 마음에 듭니다...",
            "가성비 괜찮아요,귀여워요",
            "발 편합니다..맘에 들어요",
            "발 볼이 조금 조금 좁음신발은 푹신하고 이쁨",
            "이뿌고 잘맞아요240정사이즈예요부드럽고신어면 편해요",
            "굽이 적당하고 주문당시 검정색 품절로 구매했는데 요즘 신기 좋네요버클 부분 큐빅 장식은 개인적으로 별로네요편하게 신기 좋아요",
            "너무 편하고 예쁘네요~발볼이 없는 칼발인데 맞춤처럼 꼭 맞아서 편합니다.원래 240-245 신다가 살이 많이 찌니까 250이 됐는데 어떤건 또 너무 커서 실패하기도 하는데 이건 길이는 조금 낙낙하지만 발볼과 발등을 잘 잡아줘서 편합니다.구두 처음 신으면 발뒷꿈치랑 발가락이랑 잘 까지는 편인데 아주 편하게 잘 신고 나갔다왔습니다.요즘 계속 운동화만 신었는데 오랜만에 구두 신으니까 단정해 보이고 기분 전환되서 좋네요.",
            "한사이즈 올렸더니 커요. 헐떡거리는데245로 교환하는 비용도 세고, 또 교환했는데혹여 발가락이라도 아프면.. 그래서 발바닥에다이소에서 천원짜리 앞꿈치쿠션패드하나사서 붙였더니 좀낫네요신발은 정말 예뻐요. 끈 안만져도 그냥 쑥 신으면되고.. 편합니다"
        ]
    },
    {
        "제품카테고리": "여성용",
        "제품명": "피카딜리 PICCADILLY 승무원구두 160081 메리제인 펌프스_2종 3.5cm",
        "링크": "https://prod.danawa.com/info/?pcode=65457479&cate=18242491",
        "가격": "76,790",
        "상세설명": "여성용 / 펌프스(미들힐)",
        "리뷰": [
            "착화감이 좋고 디자인도 마음에 들어요 발볼이 넓은편인데도 신발 자체가 편해서 문제 없이 잘 신을 듯 싶어요구두 240신는데 eu37 구매했더니 딱 맞네요!",
            "상품 품질이 좋습니다. 마음에 들어요!",
            "배송잘받았습니다 배송잘받았습니다",
            "배송잘받았습니다 배송잘받았습니다",
            "굉장히편해요굿굿맘에들어요"
        ]
    },
    {
        "제품카테고리": "구두",
        "제품명": "소다 투웨이 펌프스 ALS310",
        "링크": "https://prod.danawa.com/info/?pcode=18910331&cate=18242491",
        "가격": "180,340",
        "상세설명": "구두 / 여성용 / 펌프스(미들힐) / 굽종류: 청키힐 / 민자 / 메리제인 / 소재: 천연가죽 / 총굽: 5cm / 색상: 블랙",
        "리뷰": [
            "신발 편해요. 오른쪽왼쪽 발 사이즈가 달라서 밑창대주셨어요.",
            "신발 편해요. 오른쪽왼쪽 발 사이즈가 달라서 밑창대주셨어요.",
            "스트랩까지 활용도 좋을 거 같고 발이 진짜 편해서 구매했어요 어디든지 잘 어울릴거 같아요. 저는 235인데 구두는 볼생각해서 240 신으니까 딱 좋은 거 같습니다 모두 구매하세요오",
            "배송이 빨라서 좋아요 살짝 넉넉하게 나와서 발볼이 넓어도 편해요",
            "지인이 구매한거 보고 너무 편하고 이뻐서구매합니다. 스트랩끈 불량이었는데 빠른 교환 맘에 들어요",
            "구두가 너무 편하고 이쁩니다. 소다 제품을 처음 신었는데 너무 발이 편하고 좋아요. 이제 소다 제품을 자주 이용할것 같네요",
            "소다 구두를 처음 사서 신었는데 이렇게 ㄱ 편하고 이쁠수가 없어요. 앞으로 소다 제품만 신어야 겠습니다."
        ]
    },
    {
        "제품카테고리": "구두",
        "제품명": "허시파피 여성 발 편한 경량 심플 4cm 몰드창 세미정장 로퍼 3fr451",
        "링크": "https://prod.danawa.com/info/?pcode=74569310&cate=18242491",
        "가격": "128,270",
        "상세설명": "구두 / 여성용",
        "리뷰": [
            "리뷰 없음"
        ]
    },
    {
        "제품카테고리": "여성용",
        "제품명": "케즈 조이 캔버스 라인 메리제인 5XM02351G021",
        "링크": "https://prod.danawa.com/info/?pcode=35343575&cate=18242491",
        "가격": "46,610",
        "상세설명": "여성용 / 펌프스(미들힐)",
        "리뷰": [
            "리뷰 없음"
        ]
    },
    {
        "제품카테고리": "여성용",
        "제품명": "아멜리에 Juliette 여성 소가죽 슬림 메리제인 펌프스 AM241001",
        "링크": "https://prod.danawa.com/info/?pcode=35251388&cate=18242491",
        "가격": "85,600",
        "상세설명": "여성용 / 펌프스(미들힐)",
        "리뷰": [
            "리뷰 없음"
        ]
    },
    {
        "제품카테고리": "구두",
        "제품명": "슈펜 가드너 스퀘어 리본 플랫슈즈 HPWWFDA01S",
        "링크": "https://prod.danawa.com/info/?pcode=21649520&cate=18242491",
        "가격": "12,250",
        "상세설명": "구두 / 여성용 / 플랫 / 장식 / 소재: 인조가죽 / 총굽: 1.5cm / 색상: 화이트, 블랙, 옐로우, 라이트베이지, 라이트그린, 블루, 실버, 라이트바이올렛 / 출시가: 19,900원",
        "리뷰": [
            "사이즈 크게 나와서 한사이즈 작게 시키셔도 됩니다원래 발볼 넓어서 운동화는 235 신고구두너 로퍼같이 볼 좁은 신발은 240 신는데,이건 235 잘맞았고 뒤꿈치 부분도 아주 편했습니다",
            "배송을 빠르게 해주셨네요~색상도 이쁘고 발도 편해요",
            "색상이 너무 예뻐서 구매하였습니다. 늘어나서 발도 편합니다.",
            "색상이 예쁘네요~~~",
            "푹신하고 조금 큰편인거 같아요",
            "편하고 신기 좋아요.",
            "편하고 신기 좋아요.",
            "좀커서아쉽지만다른부분은맘에듭니다.",
            "친구가 이쁘다고 해서 같은걸로 구매했어요 쿠션이 있어 발이 편하고 여름에 신기에 시원해보이거 이쁩니다",
            "디자인예쁘고 푹신해서좋아요색상이 조금더 다크한 카키였음 더 고급스러웠을텐데",
            "넘이쁩니다 편하구요",
            "바닥은 푹신해요. 정사이즈보다조금 큰듯하네요. 그래선지 발뒷꿈치가 닿지않아서 좋아요.발볼이 넓으면퍼져보입니다. 가격대비 슈펜신발강추합니다",
            "색상이랑 디자인 넘이쁘네요 화면과 똑같아요 근데 사이즈가 크게 나와서 깔창을 깔아야 될듯 합니다 다른색상 구매 하려 했더니 할인 종료 되었네요",
            "하루전이었으몀 더 저렴하게 샀을텐데큰기대안했는데새신발이니 당연 아픈거고 뒷꿈치도 빨개졌다 싶은데물집까지는 안생기더라구요사이즈는 정사이즈고낮은굽에 비해 폭신함이 있어허리 덜아플거같아요",
            "반 사이즈 작게 시키세요뒷꿈치 벗겨집니다",
            "원래 235신는데 칼발이라 230주문했어요살짝 끼는 느낌인데 신다보면 늘어날거 같아요",
            "배송 빠르게 잘 받았구 상품도 괜찮아요!!!",
            "좋아요 좋아요 좋아요 좋아요 좋아요 좋아요",
            "240신는데 이 슈즈는 살짝 큽니다앞이 짧아서 벗겨져서 중간에 밴드 하나 넣음 좋을 듯 해요작은 것보다 나으니까 싸게 봄에 잘 신을께요~",
            "쿠션감좋아요. 고무신느낌 많이없어서좋네요.봄에잘신을게요.칼발250인데 걸을때 살짝 여유잇어요.양말신음 잘맞구요.정사이즈추천"
        ]
    },
    {
        "제품카테고리": "구두",
        "제품명": "어썸듀 로퍼 ADS316",
        "링크": "https://prod.danawa.com/info/?pcode=15328781&cate=18242491",
        "가격": "177,990",
        "상세설명": "구두 / 여성용 / 체인로퍼(장식) / U팁 / 꺾어신는신발(바부슈) / 소재: 천연가죽 / 총굽: 1cm / 색상: 베이지, 아이보리, 블랙",
        "리뷰": [
            "리뷰 없음"
        ]
    },
    {
        "제품카테고리": "구두",
        "제품명": "데일라잇뉴욕 Flat Rae DYCH6074",
        "링크": "https://prod.danawa.com/info/?pcode=9369747&cate=18242491",
        "가격": "34,490",
        "상세설명": "구두 / 여성용 / 플랫 / 민자 / 소재: 천연가죽 / 총굽: 2cm / 색상: 블랙, 브라운, 그레이",
        "리뷰": [
            "리뷰 없음"
        ]
    },
    {
        "제품카테고리": "구두",
        "제품명": "엘칸토 경량 쿠션UP 미들 펌프스 여성구두 LCWD29U513",
        "링크": "https://prod.danawa.com/info/?pcode=75674363&cate=18242491",
        "가격": "118,950",
        "상세설명": "구두 / 여성용 / 펌프스(미들힐)",
        "리뷰": [
            "리뷰 없음"
        ]
    },
    {
        "제품카테고리": "여성용",
        "제품명": "엘칸토 몰04 여성 펌프스 LCWO15U313 S",
        "링크": "https://prod.danawa.com/info/?pcode=45024080&cate=18242491",
        "가격": "75,740",
        "상세설명": "여성용 / 펌프스(미들힐)",
        "리뷰": [
            "리뷰 없음"
        ]
    },
    {
        "제품카테고리": "여성용",
        "제품명": "슈썸 여성 캐주얼 금 장식 디자인 단화 블로퍼 LK-BL14",
        "링크": "https://prod.danawa.com/info/?pcode=45127808&cate=18242491",
        "가격": "13,060",
        "상세설명": "여성용 / 로퍼",
        "리뷰": [
            "리뷰 없음"
        ]
    },
    {
        "제품카테고리": "구두",
        "제품명": "페라가모 바라 퀼팅 펌프스 0672114",
        "링크": "https://prod.danawa.com/info/?pcode=8487333&cate=18242491",
        "가격": "554,180",
        "상세설명": "구두 / 여성용 / 플랫 / 장식 / 소재: 천연가죽 / 총굽: 3cm / 색상: 블랙",
        "리뷰": [
            "백화점에서 신어보고 주문햇는데 D볼이라 그런지 좀 큰듯합니다.그래도 너무 맘에 들어요. 기본 펌프스에 퀼팅이 들어가잇어서 더 고급진거 같아요.포장박싱이랑 정품 확인서 까지 롯데아이몰에서 발급해서 넣어두었어요.",
            "정사이즈로 나왔고 워낙 발이 편한 브랜드라 자주 이용합니다.",
            "좋은 가격에 잘 구매했습니다.,",
            "좋은 가격에 잘 구매했습니다."
        ]
    },
    {
        "제품카테고리": "플랫",
        "제품명": "스케쳐스 Modern Comfort Womens 여성용 Arya-Oh So Sweet 핸즈 프리 슬립온 메리 제인 플랫 블랙. 13..",
        "링크": "https://prod.danawa.com/info/?pcode=90981611&cate=18242491",
        "가격": "135,800",
        "상세설명": "플랫 / 메리제인",
        "리뷰": [
            "리뷰 없음"
        ]
    },
    {
        "제품카테고리": "여성용",
        "제품명": "마놀로블라닉 마놀로 블라닉 WOMEN 하이힐 71I0C4025 레드 1630923",
        "링크": "https://prod.danawa.com/info/?pcode=61399589&cate=18242491",
        "가격": "2,423,080",
        "상세설명": "여성용 / 펌프스(미들힐) / 펌프스(하이힐)",
        "리뷰": [
            "리뷰 없음"
        ]
    },
    {
        "제품카테고리": "구두",
        "제품명": "스타카토 펌프스 LIZARD02-24S-EDK62",
        "링크": "https://prod.danawa.com/info/?pcode=33409748&cate=18242491",
        "가격": "67,670",
        "상세설명": "구두 / 여성용 / 펌프스(미들힐) / 굽종류: 스틸레토힐 / 장식 / 슬링백 / 소재: 천연가죽 / 총굽: 4.5cm / 색상: 레드",
        "리뷰": [
            "고급스러운 구두예요"
        ]
    },
    {
        "제품카테고리": "여성용",
        "제품명": "핏플랍 델리카토 우븐 블랙 여성 발레리나 플랫슈즈_FFSO5E011BK",
        "링크": "https://prod.danawa.com/info/?pcode=88452284&cate=18242491",
        "가격": "109,310",
        "상세설명": "여성용 / 플랫 / 소재: 합성섬유 / 굽 높이: 2.2cm",
        "리뷰": [
            "사진과 동일 핏플랍을 즐겨서 신는데이번 제품은 크게 나온듯설명도없이 사이즈교환비를 받는것은 불만",
            "발펀하고 치마,바지 모두 예쁘게 어울려요",
            "진짜 편하고 이뻐요정사이즈 선택했는데 맨발로 신고 6시간 동안 걸어 다니고 버스타고 했는데 착용감 아주 좋아요"
        ]
    },
    {
        "제품카테고리": "구두",
        "제품명": "세라 에디션 하객룩 캐주얼 구두 펌프스 O55P239",
        "링크": "https://prod.danawa.com/info/?pcode=75613052&cate=18242491",
        "가격": "94,130",
        "상세설명": "구두 / 여성용 / 펌프스(미들힐)",
        "리뷰": [
            "크기가 살짝 여유있지만 스트랍이 잡아주니 괜찮아요. 발볼있고 저녁까지 신기에 너무편해요"
        ]
    },
    {
        "제품카테고리": "여성용",
        "제품명": "까스따네르 카스타네 CASTANER 여성 FLATS KAMPALA 에스파듀 KAMPALA 001_NEGRO BLACK 2",
        "링크": "https://prod.danawa.com/info/?pcode=45053243&cate=18242491",
        "가격": "140,060",
        "상세설명": "여성용 / 플랫",
        "리뷰": [
            "리뷰 없음"
        ]
    },
    {
        "제품카테고리": "여성용",
        "제품명": "페라가모 바라 젤리 펌프스 블랙 03-5656-726363",
        "링크": "https://prod.danawa.com/info/?pcode=62219075&cate=18242491",
        "가격": "358,080",
        "상세설명": "여성용 / 펌프스(미들힐)",
        "리뷰": [
            "리뷰 없음"
        ]
    },
    {
        "제품카테고리": "구두",
        "제품명": "세라 실크 패브릭 펌프스힐 S21P514",
        "링크": "https://prod.danawa.com/info/?pcode=21730067&cate=18242491",
        "가격": "41,700",
        "상세설명": "구두 / 여성용 / 펌프스(하이힐) / 굽종류: 스틸레토힐 / 장식 / 소재: 패브릭 / 총굽: 7cm / 색상: 베이지, 블랙 / 출시가: 338,000원",
        "리뷰": [
            "너무 예쁩니다. 잘 신을께요"
        ]
    },
    {
        "제품카테고리": "구두",
        "제품명": "Camper 샌들 FW24 K201671-002 TWINS 0 5742580",
        "링크": "https://prod.danawa.com/info/?pcode=92217050&cate=18242491",
        "가격": "220,511",
        "상세설명": "구두 / 여성용",
        "리뷰": [
            "리뷰 없음"
        ]
    },
    {
        "제품카테고리": "알 수 없음",
        "제품명": "엘칸토 여성 초경량스니커즈LCWC51U413",
        "링크": "https://prod.danawa.com/info/?pcode=34117664&cate=18242491",
        "가격": "75,946",
        "상세설명": "여성용",
        "리뷰": [
            "리뷰 없음"
        ]
    },
    {
        "제품카테고리": "구두",
        "제품명": "프리웨이 여성 자수 펀칭 로퍼 2종 RICSLC5155WFREK",
        "링크": "https://prod.danawa.com/info/?pcode=77982035&cate=18242491",
        "가격": "68,730",
        "상세설명": "구두 / 여성용",
        "리뷰": [
            "리뷰 없음"
        ]
    },
    {
        "제품카테고리": "알 수 없음",
        "제품명": "에스콰이아 여성화 여성로퍼 EQBFHQ520",
        "링크": "https://prod.danawa.com/info/?pcode=34071290&cate=18242491",
        "가격": "65,420",
        "상세설명": "여성용",
        "리뷰": [
            "리뷰 없음"
        ]
    },
    {
        "제품카테고리": "구두",
        "제품명": "엠무크 몰리 소가죽 플렉스 로퍼 516323810",
        "링크": "https://prod.danawa.com/info/?pcode=30273959&cate=18242491",
        "가격": "82,620",
        "상세설명": "구두 / 여성용 / 페니로퍼 / 굽종류: 청키힐 / U팁 / 소재: 천연가죽 / 총굽: 4cm / 색상: 블랙 / 출시가: 189,000원",
        "리뷰": [
            "회사에 신고 다니기 위해 샀어요. 심플하고 클래식한 디자인이고 발바닥이 푹신푹신해서 아주 편해요.제가 발볼이 많이 넓은데 잘 맞아요. 다만 칼발인 분들은 너무 클 수 있을거 같아요.",
            "편하고 무난한 디자인이라 거의 매일 신고 다녀요",
            "가볍고 편합니다 최근에 구입한 신발 중 제일 잘 산거 같아요~",
            "좋은 신발은 좋은곳으로 데려다준대요. 좋은곳으로 고고고"
        ]
    },
    {
        "제품카테고리": "여성용",
        "제품명": "제옥스 스페리카 EC15 여성 데일리 로퍼 블랙-8GXWWD4F1M",
        "링크": "https://prod.danawa.com/info/?pcode=67640411&cate=18242491",
        "가격": "182,350",
        "상세설명": "여성용 / 로퍼",
        "리뷰": [
            "다른분 말씀처럼 발볼이 너무 불편하네요그래도 제옥스데 라는 생각으로 주문했는데 처음 출근할때 신고 울뻔했어요ㅡㅡ발볼은 조이고 앞뒤는 미끄덩거려서 벗겨지고 ... 그래서 발볼 ?히는 도구를 사서 넓히고 있어요.",
            "한치수 크게 신청했는데도 매우작고발이 엄청 불편하고 신발이 무겁네요~매우실망인데다 박뭄비도 6000원씩이나!!!"
        ]
    },
    {
        "제품카테고리": "알 수 없음",
        "제품명": "핏플랍 F-모드 레더 흰색 여성 더비 로퍼 FFSO4F572WT",
        "링크": "https://prod.danawa.com/info/?pcode=64776632&cate=18242491",
        "가격": "104,910",
        "상세설명": "여성용",
        "리뷰": [
            "리뷰 없음"
        ]
    },
    {
        "제품카테고리": "구두",
        "제품명": "캘빈클라인 여성 펌프스 구두 하이힐 Brady 200393 정장 여성화 신발",
        "링크": "https://prod.danawa.com/info/?pcode=91244006&cate=18242491",
        "가격": "157,040",
        "상세설명": "구두 / 여성용 / 펌프스(하이힐)",
        "리뷰": [
            "리뷰 없음"
        ]
    },
    {
        "제품카테고리": "구두",
        "제품명": "피카딜리 160101 스퀘어슬링백힐 4.5CM 160101BLACK",
        "링크": "https://prod.danawa.com/info/?pcode=90517676&cate=18242491",
        "가격": "83,520",
        "상세설명": "구두 / 여성용",
        "리뷰": [
            "리뷰 없음"
        ]
    },
    {
        "제품카테고리": "여성용",
        "제품명": "르메르 여성 버클 스퀘어 토 발레리나 플랫 슈즈_FO0015LL0023BK999",
        "링크": "https://prod.danawa.com/info/?pcode=56104991&cate=18242491",
        "가격": "871,050",
        "상세설명": "여성용 / 메리제인 / 소재: 양가죽",
        "리뷰": [
            "리뷰 없음"
        ]
    },
    {
        "제품카테고리": "여성용",
        "제품명": "세라 여성 소가죽 컴포트 드라이빙 로퍼 단화 슈즈 TCP21604 컬러 3종 1CM",
        "링크": "https://prod.danawa.com/info/?pcode=45029282&cate=18242491",
        "가격": "57,510",
        "상세설명": "여성용 / 펌프스(미들힐)",
        "리뷰": [
            "크게나왔어요 240-245 신는데 245가 많이 여유로워요 신발 볼도 넓어요"
        ]
    },
    {
        "제품카테고리": "구두",
        "제품명": "허시파피 여성 소가죽 시스루 슬링백 펌프스 3FR4001/4002 230979",
        "링크": "https://prod.danawa.com/info/?pcode=79606214&cate=18242491",
        "가격": "62,410",
        "상세설명": "구두 / 여성용 / 펌프스(미들힐)",
        "리뷰": [
            "리뷰 없음"
        ]
    },
    {
        "제품카테고리": "구두",
        "제품명": "포멜카멜레 보우멜리 플랫 펌프스 2CM FLG1F1SP007 2COLOR",
        "링크": "https://prod.danawa.com/info/?pcode=75200492&cate=18242491",
        "가격": "48,730",
        "상세설명": "구두 / 여성용 / 펌프스(미들힐)",
        "리뷰": [
            "리뷰 없음"
        ]
    },
    {
        "제품카테고리": "여성용",
        "제품명": "탠디 여성 사이드오픈 펌프스 7cm_W12M3005D",
        "링크": "https://prod.danawa.com/info/?pcode=49882097&cate=18242491",
        "가격": "151,800",
        "상세설명": "여성용 / 펌프스(미들힐) / 굽 높이: 7cm",
        "리뷰": [
            "리뷰 없음"
        ]
    },
    {
        "제품카테고리": "구두",
        "제품명": "엠미소페 소가죽 플랫 512135501",
        "링크": "https://prod.danawa.com/info/?pcode=15180875&cate=18242491",
        "가격": "70,500",
        "상세설명": "구두 / 여성용 / 플랫 / 민자 / 메리제인 / 소재: 천연가죽 / 총굽: 2cm / 색상: 블랙, 와인 / 출시가: 139,000원",
        "리뷰": [
            "가죽이 조금 오래된 느낌이 있어서 별 하나 뺐어요., 디자인 슬림하고 편하고 예쁩니다. 가죽인데 가격도 저렴해서 검정도 구매했어요. 가죽은 검정이 더 고급진 느낌이 들긴합니다",
            "좋은 가격에 잘 구매했습니다.사이즈는 잘맞아요발에 살아 없는 편인데 발볼이 조금 넓어서 그런지끈이 조금 타이트해서 하는데 조금 힘드네요밑창에 굽 박은 흔적이 보여서 조금 아쉽긴하네요엄청 싼 구두도 아닌데 말이죠구두굽이 조금 닳으면 저 못이 튀어나올 것 같은데거슬리지 않을까 염려가 되네요",
            "발볼이 넓은데 편안해요!다만 바닥이 좀 딱딱하긴 해서 걸을 때 또각또각 소리는 납니다...! 그래도 가격 대비 만족스럽습니다!",
            "미소페 소가죽 플랫, 정말 마음에 듭니다. 심플하면서도 고급스러운 디자인이 보기 좋고, 좋은 소재 덕분에 오랫동안 신을 수 있을 것 같습니다. 착화감까지 편안하다면 더할 나위 없이 좋겠습니다. 구매에 만족합니다. 흰색 깔창도 함께 받았습니다.",
            "비슷한 디자인에 저렴이로 살까하다 그래도 미소페꺼 샀는데 잘산거 같아요.딱 맞는 사이즈에 발도 편하고 디자인도 깔끔하니 마음에 듭니다.",
            "한치수 올려 구매하니 편안하게 잘 맞아요 신발 깔끔하게 이뻐요",
            "가죽의 질이 좋고 디자인 슬림하고 편합니다. 정장, 캐주얼 모두 어울릴것 같아요",
            "사이즈가 작게나와서 발이 아프네요! 신었을때 발모양은 예뻐요",
            "아주 쳔하진않지만 괜찮은거 같아요. 가죽은 좀 딱딱힙니다",
            "아주 편하게 잘 신고 있어요. 일부러 한사이즈 크게 구입했는데 끈이 있어서 헐떡이지 않고 잘 맞네요.",
            "착화감도 좋고 편하게 잘 신고 다닐 것 같아요",
            "좀 딱딱하긴 한데 예뻐요.",
            "깔끔한 디자인이 맘에 드네요",
            "리뷰 작게 나왓다구 했는데... 정사이즈 시켰더니 좀 발이 아파요",
            "귀엽고 편하고 좋으네요양말에 신어도 끼지않고 좋아요~잘신을게요",
            "너무 마음에 듭니다. 편하고 여러옷에 맞춰 신기 좋아요",
            "무난하게 신고 다니기 좋아요.",
            "앞볼이 작지않고 아프지않아서 신기, 좋아요",
            "발이 통통한편인데 240은 너무 딱맞아 245로 구매하니 잘맞아요",
            "생각했던 것 만큼 예쁩니다~ 여기저기 잘 신을 것 같아요"
        ]
    },
    {
        "제품카테고리": "여성용",
        "제품명": "소다 여성 세미 캐쥬얼 4센치굽 데일리 로퍼FLS432LS10",
        "링크": "https://prod.danawa.com/info/?pcode=37388957&cate=18242491",
        "가격": "86,800",
        "상세설명": "여성용 / 펌프스(미들힐)",
        "리뷰": [
            "평소 240사이즈보다는 조금커서 양말신고 신으니 괜찮네요 앞부분이 생각보다 볼이 좁아서조금 불편해도 신을만 합니다."
        ]
    },
    {
        "제품카테고리": "구두",
        "제품명": "가버 구두 컴포트 여성 플랫 구두 네이비 GB62.623.56",
        "링크": "https://prod.danawa.com/info/?pcode=92132036&cate=18242491",
        "가격": "102,620",
        "상세설명": "구두 / 여성용 / 플랫",
        "리뷰": [
            "리뷰 없음"
        ]
    },
    {
        "제품카테고리": "구두",
        "제품명": "피카딜리 279033 슬링백 블랙페이턴트 2.5CM 279033BLACKP",
        "링크": "https://prod.danawa.com/info/?pcode=78092483&cate=18242491",
        "가격": "91,130",
        "상세설명": "구두 / 여성용 / 로퍼",
        "리뷰": [
            "리뷰 없음"
        ]
    },
    {
        "제품카테고리": "여성용",
        "제품명": "세라 여성 포인트 토 슬림 슬링백_A52G407",
        "링크": "https://prod.danawa.com/info/?pcode=73001768&cate=18242491",
        "가격": "77,180",
        "상세설명": "여성용 / 펌프스(미들힐) / 슬링백 / 소재: 가죽 / 굽 높이: 5cm",
        "리뷰": [
            "너무 잘빠진 구두입니다~ 이뻐요 아직 신고 나가지는 않았지만 편하길 바래봅니다",
            "너무 잘빠진 구두입니다~ 이뻐요 아직 신고 나가지는 않았지만 편하길 바래봅니다"
        ]
    },
    {
        "제품카테고리": "여성용",
        "제품명": "베어파우 여성 AVA 메리제인_K3018030RB-W",
        "링크": "https://prod.danawa.com/info/?pcode=88611020&cate=18242491",
        "가격": "42,920",
        "상세설명": "여성용 / 플랫 / 메리제인 / 소재: PVC",
        "리뷰": [
            "리뷰 없음"
        ]
    },
    {
        "제품카테고리": "구두",
        "제품명": "흐꺙 하모니 발레리나 스킨 플랫 TT-00051",
        "링크": "https://prod.danawa.com/info/?pcode=17506658&cate=18242491",
        "가격": "105,500",
        "상세설명": "구두 / 여성용 / 플랫 / 장식 / 소재: 천연가죽 / 벨벳 / 총굽: 1cm / 색상: 오크레 / 출시가: 138,000원",
        "리뷰": [
            "235 사이즈라서 조금 큽니다. 그래도 편하고 예쁘네요.",
            "발이 편하고 색이 너무 예쁩니다^^♡",
            "제발엔 너무나 편하게 잘 맞아요",
            "제발엔 너무나 편하게 잘 맞아요",
            "아주예뻐요~~^^주위에서 예쁘다고 난리예요^^",
            "착화감 편하고 색감도 봄봄입니다."
        ]
    },
    {
        "제품카테고리": "구두",
        "제품명": "바바라 5cm 데일리 펌프스 AAI241",
        "링크": "https://prod.danawa.com/info/?pcode=77102612&cate=18242491",
        "가격": "132,960",
        "상세설명": "구두 / 여성용 / 펌프스(미들힐)",
        "리뷰": [
            "리뷰 없음"
        ]
    },
    {
        "제품카테고리": "알 수 없음",
        "제품명": "착한구두 오코넬 통굽 로퍼힐 LHLTS1g809",
        "링크": "https://prod.danawa.com/info/?pcode=33823169&cate=18242491",
        "가격": "40,410",
        "상세설명": "여성용",
        "리뷰": [
            "정말 착한 구두인 듯 합니다.키 작은 저에게 굽 높은 구두를 신고 올 봄 나들이를 가야겠어요.ㅎ",
            "사이즈가 좀 커요.",
            "푹신하구 부드러운데 살짝 무겁네요.냄새는 나지않아요..잘신고 다닐거같아요.",
            "잘받았습니다 감사합니다~",
            "생각보다 신발이 무겁고 발이 불편하네요",
            "배송 완전 빠릅니다. 묵직하지만 부드럽고 편해요.",
            "생각보다 구두가 무거워요..",
            "리뷰보고 기대를 크게는 않했는데 냄새는 별로 않나고 제 맘에는 쏙 드네요",
            "기죽냄새가 너무 심해서 일주일넘게 배란다행다행히 냄새는 빠졌네요엄지발가락이 조금 부닫치긴한데신발은 높이에 비해 편합니다",
            "일단 싸이즈 크고요.많이 안좋은 냄새가 많이많이 납니다.건강에 안좋을듯요.그리고 많이 무겁습니다ㅜ",
            "신발 너무편하고 이뻐요 부드럽구요아주맘에들어요",
            "이쁜데냄새가 너무 심해요도대체...일회용도아니고디자인 맘에드니깐가격싸니깐적당히 신고 보내줘야겠네요",
            "너무편하고 안신은거처럼 가볍네오ㅡ",
            "신발 고무냄새가 좀 심합니다.",
            "너무 맘에 듭니다.감사합니다.^^",
            "착한 가격에 편하고 좋아요~"
        ]
    },
    {
        "제품카테고리": "구두",
        "제품명": "인텐스바이엘칸토 스퀘어 로퍼 LCWD82I14C",
        "링크": "https://prod.danawa.com/info/?pcode=15663590&cate=18242491",
        "가격": "29,600",
        "상세설명": "구두 / 여성용 / 로퍼 / U팁 / 소재: 인조가죽 / 총굽: 2.5cm / 색상: 블랙, L그레이, D베이지 / 출시가: 45,000원",
        "리뷰": [
            "싸이즈 살 맞고 색상도 화면과 동일하고 실내에서 잠깐 신어 봤는데 불편한건 없어요 잘 신을 것 같아요",
            "금방늘어날것같지만 걸을때 발등꺽이는부분에 굵게 선이가서조금쪼이면서 아파요 신발은이쁘고 발은 길어보여서커 발보여요",
            "크랙이 있어 멋스러운 신발.입니다.적당히 편한신발. 잘 신을듯",
            "디자인이은 이쁩니다. 근데 뻣뻣한 느낌이 들고 생각했던 색상보다 밝아 좀 아쉽습니다.",
            "신발 볼이 작은것 같아요집에서 잠깐 신었는데 발이 아프네요",
            "앞코가 달랑말랑하는데 늘어나겠죠이쁘네요",
            "맘에드는 로퍼를 착한가격에 득템했어요",
            "볼이 좁아요 그리고 바닥이 미끄러워요",
            "가격대비. 대박. 멋수러워요",
            "상품 잘받았습니다 저렴하게 잘 구입했습니다",
            "제품에 만족합니다",
            "엘칸토제품이라 믿고 저렴 해서 구매 했슴. 싼티 팍팍~ 밑창은 넘 미끄럽고 프라스틱종류로 숩을해서 팔다니 깜놀랬슴 신고 걸어 보다 미끄럼. 돈들여 밑창 덧대고 구두굽도 덧대서 신을려고 수선 했슴. 제품도 제대로 된걸 파세요.택배비 땜시 수선 했슴.",
            "신발에 무늬가 있네요 ㅎㅎ 근데 나쁘지않아요 그리고 굽도 적당해서 편할거 같은데 제가 발볼이 넓어서 ㅠㅠ 앞코도 일자로 보여서 그게좀 전 아쉽네요 개인적인 생각입니다"
        ]
    },
    {
        "제품카테고리": "구두",
        "제품명": "탠디 공단 샌들 722043 W-806",
        "링크": "https://prod.danawa.com/info/?pcode=17272373&cate=18242491",
        "가격": "268,000",
        "상세설명": "구두 / 여성용 / 펌프스(미들힐) / 굽종류: 스틸레토힐 / 민자 / 메리제인 / 사이드오픈+슬링백 / 총굽: 6cm / 색상: 퍼플",
        "리뷰": [
            "리뷰 없음"
        ]
    },
    {
        "제품카테고리": "구두",
        "제품명": "비버리힐스폴로클럽 여성 천연소가죽 미니멀 로퍼",
        "링크": "https://prod.danawa.com/info/?pcode=15267281&cate=18242491",
        "가격": "33,010",
        "상세설명": "구두 / 여성용 / 로퍼 / U팁 / 소재: 천연가죽 / 총굽: 3.5cm / 속굽: 1cm / 색상: 블랙, 아이보리, 토프그레이, 카키브라운, 민트, 피치핑크 / 출시가: 39,800원",
        "리뷰": [
            "이 가격에 마감 이 정도에 소가죽에 (냄새는 엄청 납니다. 하루 정도 놔두세요..) 푹신함까지 감사할 정도에요. 굽 높이도 너무 낮지도 않고 딱 좋은데..디자인이 좀..남자 구두 같아요 ㅎㅎㅎ 좋게 말하면 딱 락포트 같아 보이는데 ㅋㅋㅋㅋ앞쪽은 너무 날카롭지 않은 긴 둥글형이고 뒷꿈치는 펑퍼짐.. 앞쪽은 발볼이 좁고 꽉 조이고, 뒷쪽은 발목을 못잡아주네요. 걸을 때 약간 뻐지는 느낌? 가성비 좋아서 그냥 신을께요.. 밝은 색이면 좀 덜 남자구두 느낌 날까요? ==;; 앞 볼을 조금만 더 넓히는게 나을 듯 하네요. 제 발등이 높아서 그럴 수 있지만요. 사이즈는 정사이즈.. 크지 않구요. 딱 맞아요!! 이건 발등이나 볼에 따라서 다르게 느낄 수 있겠네요.",
            "리뷰들 보고 사이즈 한단계 줄여서 주문했더니 딱 맞습니다. 운동화 230 신는데 이 제품 225 주문했어요. 양말 신고는 안 들어가고 얇은 스타킹 신고는 들어갑니다. 깔창이 푹신해서 신고 일어서면 무게에 눌리면서 신발 안쪽 공간이 생기는 느낌이에요. 그래서 발이 맞나봐요. 적당한 굽이 있어 좋구요. 편하게 신기 괜찮네요. 구두 밑창은 좀 미끄러운 것 같아요. 배송 빠르고 안전하게 잘 받았습니다.",
            "배송도 꼼꼼히 토프베이지가 모카색상이네요 모카색상 넘 좋아하는데 받고 신어보니 착화감이 넘 편하고 디자인 질리지않고 모던해서 가을철 신기에 취향저격이네요 바닥쿠션도 부드럽고 도툼해 길게 걸어도 아프지않아요 다음에 아이보리색상도 신고싶어요 추천해요^^",
            "예쁘네요.색상이 브라운을 생각했는데 카키색이 더 강하네요. 뭐 나쁘지않아요. 부드럽고 가볍고 바닥도 푹신하니 좋아요. 사이즈도 넉넉하고..다만 발등에 주름이 이쁘지않게 많이 잡혀서 쫌.. 그래도 싸게 잘 샀어요. 잘 신겠습니다 ~",
            "홈쇼핑제품도 교환시 왕복 택배비가 있나요? 두켤레를 샀는데 남편사이즈가 안맞아서 사이즈랑 색상교환 할려고하니 왕복 택배비를 달랍니다 삼마넌짜리신발에 택배비가 오천원이라 생각좀 해봐야겠네요 이건 좀 심한듯합니다 배송비주고 반품했어요 기분이 나빠요",
            "매번 새끼발가락이 아파 구두를 아무거나 못신었는데 이구두는 오늘 신어보니까 발가락이 끼는 느낌은 없네요 아직까지 성공인거 같고 외출후 오래신고나서도 편하길 기대해봅니다 240 정사이즈 시켰는데 잘맞습니다",
            "맨발에 신으니 착화감이 딱 좋았어요. 255라 늘 신발이 불편했는데 이렇게 편한 신발 찾기가 하늘에 별따기 같이 힘들거든요 너무너무 감사합니다 가격도 좋았습니다 다만 양말신고 작을까봐 걱정되는데 천연소가죽이니 신으면 늘어나겠지요:) 이 상품 기획하신 MD님 복 받을실꺼에요",
            "가지고있는 신발이 거의 블랙이고 가을에 어울릴거같은 토프그레이로 주문했는데 너무 튀지않아 좋습니다 아직 밖에서 신어보지 않았지만 발바닥 쿠션감도 좋고 착화감도 가볍고 좋습니다^^235정사이즈입니다~",
            "발이커서 좋은신발 찾기가 어려운데 255까지 있어서 바로 구매해봤어요. 안쪽 바닥이 퀼팅이 되어있어서 쿠션이 좋아요. 가죽도 부드러운편이에요. 단 전체적인 느낌은 수녀님스타일^^",
            "색감 디자인 다 너무 좋아요 색상도 흔하지 않고 디자인은 심플하고 240 했다가 너무커서 235 교환했어요 교환 수거 배송 전부 속전속결 2일만에 새것 받았어요 타사 보다 일처리가 되게 빠르고 좋아요",
            "신발이 가죽이라 품질은 좋으네요.. 사이즈가 많이 크게 나왔어요,평소 235신어서 235 주문했는데 양말을 신고 신어도 걸을때 자꾸 신발이 벗겨질려 합니다.",
            "정사이즈가 헐덕거린다는 상품평이 있어서 정사이즈를 주문했는데 발볼이 있어서인지 앞쪽은 끼는 느김이 있는데 헐덕이네요 좀 늘어나면 볼부분이 괜찮을것 같아 교환안하고 신을까합니다 바닥",
            "정사이즈가 헐덕거린다는 상품평이 있어서 정사이즈를 주문했는데 발볼이 있어서인지 앞쪽은 끼는 느김이 있는데 헐덕이네요 좀 늘어나면 볼부분이 괜찮을것 같아 교환안하고 신을까합니다 바닥",
            "다른 채널에서 보고 현대홈쇼핑에도 같은 물건이 있어 포인트써서 가격도 싸게 잘 샀어요 신어보니 너무 마음에 들어요! 추천합니다. 올레길도 걸었는데 발이 아프지않아 편하게 잘 신고 있어요 정장에 잘 어울립니다",
            "배송 빠름 친절하고 구두는 정 사이즈로 발볼이 약간 넓은 편인데도 신발이 편하고 좋아요.착한가격에 조은신발 잘샀네요.강추합니다!",
            "홈쇼핑 보시고사달라 하셔서엄마 선물로 보냈어요홈쇼핑보다 더 저렴히 잘 샀네요딱 정사이즈로 잘 맞고편하시데요다만화면보다 그레이색이 이쁘지는 않아 보여서조금 실망하신거 같아요^^;",
            "배송날짜에 맞춰서 깔끔하게 배송, 뒤가 헐거운데 벗겨져서 불편한정도는 아님 , 오래신으면 새끼발가락이 좀 아픔 , 디자인이 심플해서 다른 색상도 구매예정",
            "가성비 갑이네요.^^ 재질이 부드럽고 바닥도 쿠션감 좋습니다. 평소 235신는데 정사이즈에요. 잘 신을께요~~ 남편것도 같이 샀는데, 사이즈교환 신청합니다~",
            "신발. 깔끔하고 넘 좋아요.다른색상도 또 구입하고 싶어요.가격대비 색상도좋고가격도 착해서 괜찮아요.지금 또 주문해도 되는지요?",
            "너무 예뻐요~ 저번 비버리꺼 신어보고 편해서 또 시켰는데 이번건 너무 편해보이기만 하는게 아니고 살짝 굽이있어서 신발은 편한데 모양까지 갖췄네요 ㅎㅎ민트도 하나 더 주문했어요~"
        ]
    },
    {
        "제품카테고리": "여성용",
        "제품명": "내추럴라이저 NATURALIZER 로퍼 단화 구두 Cabaret 플랫폼 러그 솔 와이드 폭 1405814",
        "링크": "https://prod.danawa.com/info/?pcode=70275776&cate=18242491",
        "가격": "115,000",
        "상세설명": "여성용 / 로퍼",
        "리뷰": [
            "리뷰 없음"
        ]
    },
    {
        "제품카테고리": "여성용",
        "제품명": "오노마 오노마 ONM 호피샌들 밴딩 슬링백샌들 데일리 여름 엄지쪼리 8533421 8533421",
        "링크": "https://prod.danawa.com/info/?pcode=45192008&cate=18242491",
        "가격": "57,190",
        "상세설명": "여성용 / 펌프스(미들힐)",
        "리뷰": [
            "리뷰 없음"
        ]
    },
    {
        "제품카테고리": "구두",
        "제품명": "락포트 토탈모션 카이아 슬링 CH4325",
        "링크": "https://prod.danawa.com/info/?pcode=11067099&cate=18242491",
        "가격": "89,900",
        "상세설명": "구두 / 여성용 / 펌프스(미들힐) / 굽종류: 스틸레토힐 / 민자 / 슬링백 / 소재: 천연가죽 / 에나멜 / 총굽: 5cm / 색상: 베이지 / 출시 사이즈: 220~255mm / 출시가: 250,000원",
        "리뷰": [
            "기본 디자인의 슬링백이예요무난하게 신을 구두가 필요해서 찾아보다가 락포트가 편하다고 하고 지난번 구매한 플랫도 편하게 신고 있던터라주문해보았습니다^^스틸레토 디자인의 구두를 좋아해서 여러 브랜드 많이 신어봤는데 보통은 앞코가 좁다 보니 처음에는 편한 것 같아도발이 아파서 잘 못 신게 되는데..락포트는 일단 착화 해보니 볼 부분은 다른 브랜드 보다 여유가 있고 앞 부분이 많이 길지 않아 그런지 불편한 느낌은 없어요제품 안 쪽에 쿠션이 되어 있어서 더 나은 듯 한데 이건 신고 오래 다녀봐야 더 잘 알 수 있을 듯 싶습니다^^디자인도 색상도 무난해서 어떤 옷이든 받쳐 입기 좋을 것 같아요~",
            "정품 맞나 싶을정도로 상태 너무 이상한게 와서 교환신청하고 다시 받았어요. 처음보단 괜찮은 상품이 왔지만 역시 1년이상된 제품이고(2023.1) 이 정도면 백화점이 아니라 아울렛 가야하는거 아닌가싶긴하네요.. 다른지점에서 얼마전 락포트 구두 샀는데 박스도 다르고 구성품도 달라서 상품이 다르지만 박스도 다를 수 있나싶긴한데 이번주말에 신을 용도로 구매했기에 그냥 신으려고해요. 사이즈는 일부러 업할 필요는 없고 정사이즈이고 짙은 스킨색이에요. 화사함은 없습니다.",
            "정품 맞나 싶을정도로 상태 너무 이상한게 와서 교환신청하고 다시 받았어요. 처음보단 괜찮은 상품이 왔지만 역시 1년이상된 제품이고(2023.1) 이 정도면 백화점이 아니라 아울렛 가야하는거 아닌가싶긴하네요.. 다른지점에서 얼마전 락포트 구두 샀는데 박스도 다르고 구성품도 달라서 상품이 다르지만 박스도 다를 수 있나싶긴한데 이번주말에 신을 용도로 구매했기에 그냥 신으려고해요. 사이즈는 일부러 업할 필요는 없고 정사이즈이고 짙은 스킨색이에요. 화사함은 없습니다.",
            "4/23구매 4/29에 받았습니다. 기다린 만큼 기대가 커야되는데 신발 상태가 A급은 아닌 듯하여 속상했습니다. 내일 급한 일정으로 신어야 되어, 반품은 하지 않고 그냥 신으려합니다. 다음엔 검수 잘 해서 보내주시길 바랍니다..(신발 테두리라인 찍혀있음^_^)",
            "4/23구매 4/29에 받았습니다. 기다린 만큼 기대가 커야되는데 신발 상태가 A급은 아닌 듯하여 속상했습니다. 내일 급한 일정으로 신어야 되어, 반품은 하지 않고 그냥 신으려합니다. 다음엔 검수 잘 해서 보내주시길 바랍니다..(신발 테두리라인 찍혀있음^_^)",
            "저는 발볼이 넓고 길이는 짧은편이라 한사이즈 다운해서 주문했는데 아주 딱 잘 맞고 편해요~ 보기에도 단아하고 좋네요",
            "발볼이 넓은 편인데 착화감이 좋고 무난하게 잘 맞네요. 새신인데.. 안쪽이어서 신기로 했어요.",
            "예전에블랙컬러를샀었는데사이즈가작아서잘못신었거든요.이번엔제대로구매한거같아요.제가좋아하는스딸이예요.만족해요^^",
            "이쁘고 배송도 빨라서 만족합니다 포장도 꼼꼼했습니다기분 좋은 구매라서 좋네요.락포트야 뭐 늘 발 편한 걸로 유명하니까요가격도 무척 싼것 같아 좋습니다.",
            "상품평 많아 일단 구입했는데 편한 신발입니다 심플해서 데일리로 좋아요",
            "좋은 가격에 잘 구매했습니다.아직 신어보진 않았지만시착만 해보니 편한거같아요.굽도 적당하고 원피스에 잘 어울릴꺼같아요.",
            "바닥이 폭신폭신 편해요",
            "아직오래신어보진않았지만 착화감은 편해요",
            "아직오래신어보진않았지만 착화감은 편해요",
            "백화점에서 매진이라 하여 씨제몰 에서 더 저렴하게 구입했어요아주 편해요",
            "상품 품질이 좋습니다. 마음에 들어요!",
            "좋은 가격에 잘 구매했습니다.",
            "아울렛에서 신어보고 여기서 저렴하게 구입했네요",
            "정사이즈 입니다.",
            "락포트 힐부터 신어보고 편해서 백슬링도 구매했어요역시 편해요"
        ]
    },
    {
        "제품카테고리": "구두",
        "제품명": "페라가모 비바 발레리나 플랫 0730595",
        "링크": "https://prod.danawa.com/info/?pcode=16021286&cate=18242491",
        "가격": "787,460",
        "상세설명": "구두 / 여성용 / 플랫 / 장식 / 소재: 천연가죽 / 총굽: 2cm / 색상: 블랙 / 출시가: 1,090,000원",
        "리뷰": [
            "칼발 아닌 분들은 반사이즈 업하세요",
            "칼발 아닌 분들은 반사이즈 업하세요",
            "goodgoodgood",
            "편하게신으려고 반사이즈업했더니 발편하구좋아요.디자인도 마음에들어요?",
            "상태가 좋아요. 스크래치나 흠집 없는 상품으로 잘 왔어요. 발이 편해요.",
            "너무 발이 편하고 예뻐서 계속 신게 돼요 다른색도 사고 싶어요"
        ]
    },
    {
        "제품카테고리": "여성용",
        "제품명": "컨버스 남녀공용 척테일러 올스타 러그 힐 메리 제인_A10617C",
        "링크": "https://prod.danawa.com/info/?pcode=72926810&cate=18242491",
        "가격": "74,320",
        "상세설명": "여성용 / 펌프스(미들힐) / 메리제인",
        "리뷰": [
            "리뷰 없음"
        ]
    },
    {
        "제품카테고리": "구두",
        "제품명": "오브엠 글렌 미드힐 펌프스 S21M8210",
        "링크": "https://prod.danawa.com/info/?pcode=12159779&cate=18242491",
        "가격": "13,410",
        "상세설명": "구두 / 여성용 / 펌프스(미들힐) / 굽종류: 청키힐 / 장식 / 소재: 천연가죽 / 총굽: 5cm / 색상: 블랙, 그레이, 틸 그린, 와인 / 출시 사이즈: 220~255mm",
        "리뷰": [
            "리뷰를 읽어보니 작다고 나와서 평소에240신는데 245를 샀어요집에서 신어보니 발이 아파요가죽이 지금은 딱딱해서 그런것 같은데 자주신으면 맞을것 같아요그런데 구두신고 걸을때 딱딱소리 나는 구두 있는데 이구두가 그러네요신발 밑창을 보니 검은색으로 덧데어 있고 딱딱해서 그런가봐요 날이 풀리면 신발은 예뻐서 잘신을듯 하고 싸게 잘샀어요",
            "평소구두는240신는데상품평보고한치수크게245샀어요잘맞아요헐떡거림없습니다240샀으면작을뻔했어요발편하고안쪽에쿠션이넘좋아요족저근막염과지방패드중후군있는데쿠션감이넘좋아서신어도될거같아요그레이보다는모카브라운같아요그래서더좋아요베이지내아이보리바지에딱입니다바닥창도도톰하고미끄럼방지되어있어요이가격에살수없는가격입니다제조국도대한민국이고싸이즈있을때구매하세요",
            "가격을 본다면 일단 득탬했다고 볼수 있어요.발바닥면의 쿠션감이 아주 좋아요.단 염소가죽이라 가죽이 딱딱하고 거칠어요.사이즈는 작게 나와서 한치수 올려 신었어요.발등.뒷꿈치부분의 가죽이 딱딱해서 아파요.",
            "작다는 후기때문에 한사이즈 크게 구매했는데 바닥에 쿠션이 있어서 그런거 같아요.스타킹 신고 착용하면 잘맞고 사진보다 이쁘고 고급져요.다만 발등쪽이 가죽이라 그런지 부드럽지는 않네요",
            "디자인 가격저렴 좋아서 구입했고 오늘 처음 신어봤는데 사이즈는 한치수크게 사서 사이즈 맞고 가죽이 뻣뻣?서인지 불편합니다",
            "사이즈는 작아서 한치수 업했더니 좋고 가격이 너무 착해 만족해요. 단지 발등이 높으신분들은 힘들듯해요. 발등이 높지도 않은데 발등이 좀 아파요",
            "신발 모양은 예쁜데 부드럽지 않고 딱딱하게 느껴지고 신었을때 불편합니다. 새 신발인것을 감안하더라도 뻣뻣하고 발이 아파요",
            "발볼이 넓은분들은 한사이즈 업하세요~ 바닥은 쿠션감도좋고 편안한고 디자인도 깔끔한데 겨울이라그런지 약간 딱딱하네요",
            "가죽이 부드럽지않고 좀 딱딱합니다신발이 편하지는 않은듯합니다디자인은 유행타지 않고 무난하게 신을 수 있을둣 합니다.",
            "50대 지인 선물로 드렸는데 색깔,디자인, 바닥쿠션 너무 마음에 들고댓글에 싸이즈 한치수 크게 주문하라해서 235인데 40으로 주문해서 양말신고하루 신어 봤는데, 그사이에 늘어난모양인지살짝 헐떡인다고 하셔서 패치 주문했네요가격대비 너무 좋아요",
            "가죽이 딱딱하고 뻣뻣합니다 좀 신다보면 늘어날거라 봅니다 굽높이도 적당하고 색상도 그레이보단 모카베이지에 가까워요",
            "신발 사이즈 잘못와서 교환해서 좀 늦게왔어요신발이 조금 딱딱해요부드러울줄 알았는데저렴하게 잘 산것같아요",
            "이 가격보다 비쌀 때 블랙을 구입하여 잘 신었습니다. 발표회 때 장시간 신어도 편했는데 반 값에 물건 파는 걸 보고 베이지, 그린 구매했습니다. 색 튀지도 읺고 또 너무 맘에 들어버리네요. 가죽을 이 가격에 팔다니 혹 망설이는 분이 계시면 무조건 사세요.^^",
            "신발이 좀 딱딱해요더 신어봐야겠지만 발이 까질듯이 가격에 많은걸 원하는건 무리겠지만 가격만 생각하면 디자인도 괜찮아요",
            "오브엠 발이 편한 신발이라 예전에 즐겨 신던 것이 생각나 주문했는데 역시나 발이 편하고 구두 디자인도 예쁘네요 가격이 너무 착해서 횡재한기분입니다 봄이 되면 예쁘게 잘 신고 다니겠어요^^",
            "리뷰에 작다는 의견이 많아서 걱정 했는데 정사이즈 같아요 근데 오른쪽 발등 쪽이 좀 눌려서 아프네요 신발은 고급스럽고 예뻐요",
            "2가지색상 사고 예뻐서 또 그린색상도 구매했어요 225신는데 정사이즈로 잘맞고 신발상태 아주좋아요",
            "쿠션도 두툼해서 좋은데 발가락쪽에 사진은 안나오는데 깔창 마감처리를 제대로 못해서 오른쪽은 떠있고 완쪽은 남아서 찌그러져서 마감처리하고...이게 30만원돈 했던거라는게 조금 이해 안가네요.신는데 크게문제없어서 그냥신어요",
            "한사이즈 업해도 딱 여유없이 맞네요..재질 디자인 컬러 맘에 들어서블랙 그레이 그린 3개 구입했습니다.가성비 촤고입니다.",
            "235-240신어서 240을 주문했는데 저한테는 쪼끔커요 발볼은 좁은편인데 앞부분이 쿠션이 있어 편해요 근데 발볼부분은 여유가 없어요"
        ]
    },
    {
        "제품카테고리": "구두",
        "제품명": "제옥스 여성4센치 클레식 로퍼 2종 8TMCA1",
        "링크": "https://prod.danawa.com/info/?pcode=76011617&cate=18242491",
        "가격": "147,820",
        "상세설명": "구두 / 여성용 / 로퍼",
        "리뷰": [
            "리뷰 없음"
        ]
    }
]